{
  "type": "File",
  "start": 0,
  "end": 1038,
  "loc": {
    "start": {
      "line": 1,
      "column": 0
    },
    "end": {
      "line": 33,
      "column": 0
    }
  },
  "program": {
    "type": "Program",
    "start": 0,
    "end": 1038,
    "loc": {
      "start": {
        "line": 1,
        "column": 0
      },
      "end": {
        "line": 33,
        "column": 0
      }
    },
    "sourceType": "module",
    "body": [
      {
        "type": "ExportNamedDeclaration",
        "start": 672,
        "end": 1036,
        "loc": {
          "start": {
            "line": 19,
            "column": 0
          },
          "end": {
            "line": 32,
            "column": 1
          }
        },
        "specifiers": [],
        "source": null,
        "declaration": {
          "type": "FunctionDeclaration",
          "start": 679,
          "end": 1036,
          "loc": {
            "start": {
              "line": 19,
              "column": 7
            },
            "end": {
              "line": 32,
              "column": 1
            }
          },
          "id": {
            "type": "Identifier",
            "start": 688,
            "end": 697,
            "loc": {
              "start": {
                "line": 19,
                "column": 16
              },
              "end": {
                "line": 19,
                "column": 25
              },
              "identifierName": "cmd_abort"
            },
            "name": "cmd_abort",
            "leadingComments": null
          },
          "generator": false,
          "expression": false,
          "async": false,
          "params": [
            {
              "type": "Identifier",
              "start": 698,
              "end": 701,
              "loc": {
                "start": {
                  "line": 19,
                  "column": 26
                },
                "end": {
                  "line": 19,
                  "column": 29
                },
                "identifierName": "raw"
              },
              "name": "raw"
            },
            {
              "type": "Identifier",
              "start": 703,
              "end": 707,
              "loc": {
                "start": {
                  "line": 19,
                  "column": 31
                },
                "end": {
                  "line": 19,
                  "column": 35
                },
                "identifierName": "args"
              },
              "name": "args"
            }
          ],
          "body": {
            "type": "BlockStatement",
            "start": 709,
            "end": 1036,
            "loc": {
              "start": {
                "line": 19,
                "column": 37
              },
              "end": {
                "line": 32,
                "column": 1
              }
            },
            "body": [
              {
                "type": "ExpressionStatement",
                "start": 733,
                "end": 749,
                "loc": {
                  "start": {
                    "line": 21,
                    "column": 2
                  },
                  "end": {
                    "line": 21,
                    "column": 18
                  }
                },
                "expression": {
                  "type": "AssignmentExpression",
                  "start": 733,
                  "end": 749,
                  "loc": {
                    "start": {
                      "line": 21,
                      "column": 2
                    },
                    "end": {
                      "line": 21,
                      "column": 18
                    }
                  },
                  "operator": "=",
                  "left": {
                    "type": "Identifier",
                    "start": 733,
                    "end": 736,
                    "loc": {
                      "start": {
                        "line": 21,
                        "column": 2
                      },
                      "end": {
                        "line": 21,
                        "column": 5
                      },
                      "identifierName": "raw"
                    },
                    "name": "raw",
                    "leadingComments": null
                  },
                  "right": {
                    "type": "CallExpression",
                    "start": 739,
                    "end": 749,
                    "loc": {
                      "start": {
                        "line": 21,
                        "column": 8
                      },
                      "end": {
                        "line": 21,
                        "column": 18
                      }
                    },
                    "callee": {
                      "type": "MemberExpression",
                      "start": 739,
                      "end": 747,
                      "loc": {
                        "start": {
                          "line": 21,
                          "column": 8
                        },
                        "end": {
                          "line": 21,
                          "column": 16
                        }
                      },
                      "object": {
                        "type": "Identifier",
                        "start": 739,
                        "end": 742,
                        "loc": {
                          "start": {
                            "line": 21,
                            "column": 8
                          },
                          "end": {
                            "line": 21,
                            "column": 11
                          },
                          "identifierName": "raw"
                        },
                        "name": "raw"
                      },
                      "property": {
                        "type": "Identifier",
                        "start": 743,
                        "end": 747,
                        "loc": {
                          "start": {
                            "line": 21,
                            "column": 12
                          },
                          "end": {
                            "line": 21,
                            "column": 16
                          },
                          "identifierName": "trim"
                        },
                        "name": "trim"
                      },
                      "computed": false
                    },
                    "arguments": []
                  },
                  "leadingComments": null
                },
                "leadingComments": [
                  {
                    "type": "CommentLine",
                    "value": " raw response",
                    "start": 714,
                    "end": 729,
                    "loc": {
                      "start": {
                        "line": 20,
                        "column": 2
                      },
                      "end": {
                        "line": 20,
                        "column": 17
                      }
                    }
                  }
                ]
              },
              {
                "type": "IfStatement",
                "start": 755,
                "end": 854,
                "loc": {
                  "start": {
                    "line": 23,
                    "column": 2
                  },
                  "end": {
                    "line": 25,
                    "column": 3
                  }
                },
                "test": {
                  "type": "CallExpression",
                  "start": 759,
                  "end": 798,
                  "loc": {
                    "start": {
                      "line": 23,
                      "column": 6
                    },
                    "end": {
                      "line": 23,
                      "column": 45
                    }
                  },
                  "callee": {
                    "type": "MemberExpression",
                    "start": 759,
                    "end": 773,
                    "loc": {
                      "start": {
                        "line": 23,
                        "column": 6
                      },
                      "end": {
                        "line": 23,
                        "column": 20
                      }
                    },
                    "object": {
                      "type": "Identifier",
                      "start": 759,
                      "end": 762,
                      "loc": {
                        "start": {
                          "line": 23,
                          "column": 6
                        },
                        "end": {
                          "line": 23,
                          "column": 9
                        },
                        "identifierName": "raw"
                      },
                      "name": "raw"
                    },
                    "property": {
                      "type": "Identifier",
                      "start": 763,
                      "end": 773,
                      "loc": {
                        "start": {
                          "line": 23,
                          "column": 10
                        },
                        "end": {
                          "line": 23,
                          "column": 20
                        },
                        "identifierName": "startsWith"
                      },
                      "name": "startsWith"
                    },
                    "computed": false
                  },
                  "arguments": [
                    {
                      "type": "StringLiteral",
                      "start": 774,
                      "end": 797,
                      "loc": {
                        "start": {
                          "line": 23,
                          "column": 21
                        },
                        "end": {
                          "line": 23,
                          "column": 44
                        }
                      },
                      "extra": {
                        "rawValue": "Not currently playing",
                        "raw": "'Not currently playing'"
                      },
                      "value": "Not currently playing"
                    }
                  ]
                },
                "consequent": {
                  "type": "BlockStatement",
                  "start": 800,
                  "end": 854,
                  "loc": {
                    "start": {
                      "line": 23,
                      "column": 47
                    },
                    "end": {
                      "line": 25,
                      "column": 3
                    }
                  },
                  "body": [
                    {
                      "type": "ReturnStatement",
                      "start": 807,
                      "end": 849,
                      "loc": {
                        "start": {
                          "line": 24,
                          "column": 4
                        },
                        "end": {
                          "line": 24,
                          "column": 46
                        }
                      },
                      "argument": {
                        "type": "NewExpression",
                        "start": 814,
                        "end": 849,
                        "loc": {
                          "start": {
                            "line": 24,
                            "column": 11
                          },
                          "end": {
                            "line": 24,
                            "column": 46
                          }
                        },
                        "callee": {
                          "type": "Identifier",
                          "start": 818,
                          "end": 823,
                          "loc": {
                            "start": {
                              "line": 24,
                              "column": 15
                            },
                            "end": {
                              "line": 24,
                              "column": 20
                            },
                            "identifierName": "Error"
                          },
                          "name": "Error"
                        },
                        "arguments": [
                          {
                            "type": "StringLiteral",
                            "start": 824,
                            "end": 848,
                            "loc": {
                              "start": {
                                "line": 24,
                                "column": 21
                              },
                              "end": {
                                "line": 24,
                                "column": 45
                              }
                            },
                            "extra": {
                              "rawValue": "Not currently playing.",
                              "raw": "'Not currently playing.'"
                            },
                            "value": "Not currently playing."
                          }
                        ]
                      }
                    }
                  ],
                  "directives": []
                },
                "alternate": null
              },
              {
                "type": "IfStatement",
                "start": 860,
                "end": 972,
                "loc": {
                  "start": {
                    "line": 27,
                    "column": 2
                  },
                  "end": {
                    "line": 29,
                    "column": 3
                  }
                },
                "test": {
                  "type": "UnaryExpression",
                  "start": 864,
                  "end": 914,
                  "loc": {
                    "start": {
                      "line": 27,
                      "column": 6
                    },
                    "end": {
                      "line": 27,
                      "column": 56
                    }
                  },
                  "operator": "!",
                  "prefix": true,
                  "argument": {
                    "type": "CallExpression",
                    "start": 866,
                    "end": 914,
                    "loc": {
                      "start": {
                        "line": 27,
                        "column": 8
                      },
                      "end": {
                        "line": 27,
                        "column": 56
                      }
                    },
                    "callee": {
                      "type": "MemberExpression",
                      "start": 866,
                      "end": 880,
                      "loc": {
                        "start": {
                          "line": 27,
                          "column": 8
                        },
                        "end": {
                          "line": 27,
                          "column": 22
                        }
                      },
                      "object": {
                        "type": "Identifier",
                        "start": 866,
                        "end": 869,
                        "loc": {
                          "start": {
                            "line": 27,
                            "column": 8
                          },
                          "end": {
                            "line": 27,
                            "column": 11
                          },
                          "identifierName": "raw"
                        },
                        "name": "raw"
                      },
                      "property": {
                        "type": "Identifier",
                        "start": 870,
                        "end": 880,
                        "loc": {
                          "start": {
                            "line": 27,
                            "column": 12
                          },
                          "end": {
                            "line": 27,
                            "column": 22
                          },
                          "identifierName": "startsWith"
                        },
                        "name": "startsWith"
                      },
                      "computed": false
                    },
                    "arguments": [
                      {
                        "type": "StringLiteral",
                        "start": 881,
                        "end": 913,
                        "loc": {
                          "start": {
                            "line": 27,
                            "column": 23
                          },
                          "end": {
                            "line": 27,
                            "column": 55
                          }
                        },
                        "extra": {
                          "rawValue": "Aborted playing or paused file",
                          "raw": "'Aborted playing or paused file'"
                        },
                        "value": "Aborted playing or paused file"
                      }
                    ]
                  },
                  "extra": {
                    "parenthesizedArgument": false
                  }
                },
                "consequent": {
                  "type": "BlockStatement",
                  "start": 916,
                  "end": 972,
                  "loc": {
                    "start": {
                      "line": 27,
                      "column": 58
                    },
                    "end": {
                      "line": 29,
                      "column": 3
                    }
                  },
                  "body": [
                    {
                      "type": "ReturnStatement",
                      "start": 923,
                      "end": 967,
                      "loc": {
                        "start": {
                          "line": 28,
                          "column": 4
                        },
                        "end": {
                          "line": 28,
                          "column": 48
                        }
                      },
                      "argument": {
                        "type": "NewExpression",
                        "start": 930,
                        "end": 967,
                        "loc": {
                          "start": {
                            "line": 28,
                            "column": 11
                          },
                          "end": {
                            "line": 28,
                            "column": 48
                          }
                        },
                        "callee": {
                          "type": "Identifier",
                          "start": 934,
                          "end": 939,
                          "loc": {
                            "start": {
                              "line": 28,
                              "column": 15
                            },
                            "end": {
                              "line": 28,
                              "column": 20
                            },
                            "identifierName": "Error"
                          },
                          "name": "Error"
                        },
                        "arguments": [
                          {
                            "type": "StringLiteral",
                            "start": 940,
                            "end": 966,
                            "loc": {
                              "start": {
                                "line": 28,
                                "column": 21
                              },
                              "end": {
                                "line": 28,
                                "column": 47
                              }
                            },
                            "extra": {
                              "rawValue": "Unknown response string.",
                              "raw": "'Unknown response string.'"
                            },
                            "value": "Unknown response string."
                          }
                        ]
                      }
                    }
                  ],
                  "directives": []
                },
                "alternate": null
              },
              {
                "type": "ReturnStatement",
                "start": 978,
                "end": 1033,
                "loc": {
                  "start": {
                    "line": 31,
                    "column": 2
                  },
                  "end": {
                    "line": 31,
                    "column": 57
                  }
                },
                "argument": {
                  "type": "StringLiteral",
                  "start": 985,
                  "end": 1033,
                  "loc": {
                    "start": {
                      "line": 31,
                      "column": 9
                    },
                    "end": {
                      "line": 31,
                      "column": 57
                    }
                  },
                  "extra": {
                    "rawValue": "Aborted! Please turn any heaters off manually.",
                    "raw": "'Aborted! Please turn any heaters off manually.'"
                  },
                  "value": "Aborted! Please turn any heaters off manually."
                }
              }
            ],
            "directives": []
          },
          "leadingComments": [
            {
              "type": "CommentBlock",
              "value": "*\r\n* Parse `abort` command response.\r\n*\r\n* ### on success\r\n* ```\r\n* return 'Aborted! Please turn any heaters off manually.'\r\n* ```\r\n* ### on error\r\n* ```\r\n* return Error: 'Not currently playing.'\r\n* return Error: 'Unknown response string.'\r\n* ```\r\n* @param  {String}   raw  Raw command response string.\r\n* @param  {String[]} args Command arguments.\r\n* @return {String|Error}\r\n* @see https://github.com/Smoothieware/Smoothieware/blob/d79254323f4bb951426c6add29a4451130eaa018/src/modules/utils/simpleshell/SimpleShell.cpp#L266\r\n* @see https://github.com/Smoothieware/Smoothieware/blob/1f73659f0b0cb6142e395c3d4d7dcbaadbac870a/src/modules/utils/player/Player.cpp#L359\r\n",
              "start": 0,
              "end": 670,
              "loc": {
                "start": {
                  "line": 1,
                  "column": 0
                },
                "end": {
                  "line": 18,
                  "column": 2
                }
              }
            }
          ],
          "trailingComments": []
        },
        "leadingComments": [
          {
            "type": "CommentBlock",
            "value": "*\r\n* Parse `abort` command response.\r\n*\r\n* ### on success\r\n* ```\r\n* return 'Aborted! Please turn any heaters off manually.'\r\n* ```\r\n* ### on error\r\n* ```\r\n* return Error: 'Not currently playing.'\r\n* return Error: 'Unknown response string.'\r\n* ```\r\n* @param  {String}   raw  Raw command response string.\r\n* @param  {String[]} args Command arguments.\r\n* @return {String|Error}\r\n* @see https://github.com/Smoothieware/Smoothieware/blob/d79254323f4bb951426c6add29a4451130eaa018/src/modules/utils/simpleshell/SimpleShell.cpp#L266\r\n* @see https://github.com/Smoothieware/Smoothieware/blob/1f73659f0b0cb6142e395c3d4d7dcbaadbac870a/src/modules/utils/player/Player.cpp#L359\r\n",
            "start": 0,
            "end": 670,
            "loc": {
              "start": {
                "line": 1,
                "column": 0
              },
              "end": {
                "line": 18,
                "column": 2
              }
            }
          }
        ]
      }
    ],
    "directives": []
  },
  "comments": [
    {
      "type": "CommentBlock",
      "value": "*\r\n* Parse `abort` command response.\r\n*\r\n* ### on success\r\n* ```\r\n* return 'Aborted! Please turn any heaters off manually.'\r\n* ```\r\n* ### on error\r\n* ```\r\n* return Error: 'Not currently playing.'\r\n* return Error: 'Unknown response string.'\r\n* ```\r\n* @param  {String}   raw  Raw command response string.\r\n* @param  {String[]} args Command arguments.\r\n* @return {String|Error}\r\n* @see https://github.com/Smoothieware/Smoothieware/blob/d79254323f4bb951426c6add29a4451130eaa018/src/modules/utils/simpleshell/SimpleShell.cpp#L266\r\n* @see https://github.com/Smoothieware/Smoothieware/blob/1f73659f0b0cb6142e395c3d4d7dcbaadbac870a/src/modules/utils/player/Player.cpp#L359\r\n",
      "start": 0,
      "end": 670,
      "loc": {
        "start": {
          "line": 1,
          "column": 0
        },
        "end": {
          "line": 18,
          "column": 2
        }
      }
    },
    {
      "type": "CommentLine",
      "value": " raw response",
      "start": 714,
      "end": 729,
      "loc": {
        "start": {
          "line": 20,
          "column": 2
        },
        "end": {
          "line": 20,
          "column": 17
        }
      }
    }
  ],
  "tokens": [
    {
      "type": "CommentBlock",
      "value": "*\r\n* Parse `abort` command response.\r\n*\r\n* ### on success\r\n* ```\r\n* return 'Aborted! Please turn any heaters off manually.'\r\n* ```\r\n* ### on error\r\n* ```\r\n* return Error: 'Not currently playing.'\r\n* return Error: 'Unknown response string.'\r\n* ```\r\n* @param  {String}   raw  Raw command response string.\r\n* @param  {String[]} args Command arguments.\r\n* @return {String|Error}\r\n* @see https://github.com/Smoothieware/Smoothieware/blob/d79254323f4bb951426c6add29a4451130eaa018/src/modules/utils/simpleshell/SimpleShell.cpp#L266\r\n* @see https://github.com/Smoothieware/Smoothieware/blob/1f73659f0b0cb6142e395c3d4d7dcbaadbac870a/src/modules/utils/player/Player.cpp#L359\r\n",
      "start": 0,
      "end": 670,
      "loc": {
        "start": {
          "line": 1,
          "column": 0
        },
        "end": {
          "line": 18,
          "column": 2
        }
      }
    },
    {
      "type": {
        "label": "export",
        "keyword": "export",
        "beforeExpr": false,
        "startsExpr": false,
        "rightAssociative": false,
        "isLoop": false,
        "isAssign": false,
        "prefix": false,
        "postfix": false,
        "binop": null,
        "updateContext": null
      },
      "value": "export",
      "start": 672,
      "end": 678,
      "loc": {
        "start": {
          "line": 19,
          "column": 0
        },
        "end": {
          "line": 19,
          "column": 6
        }
      }
    },
    {
      "type": {
        "label": "function",
        "keyword": "function",
        "beforeExpr": false,
        "startsExpr": true,
        "rightAssociative": false,
        "isLoop": false,
        "isAssign": false,
        "prefix": false,
        "postfix": false,
        "binop": null
      },
      "value": "function",
      "start": 679,
      "end": 687,
      "loc": {
        "start": {
          "line": 19,
          "column": 7
        },
        "end": {
          "line": 19,
          "column": 15
        }
      }
    },
    {
      "type": {
        "label": "name",
        "beforeExpr": false,
        "startsExpr": true,
        "rightAssociative": false,
        "isLoop": false,
        "isAssign": false,
        "prefix": false,
        "postfix": false,
        "binop": null
      },
      "value": "cmd_abort",
      "start": 688,
      "end": 697,
      "loc": {
        "start": {
          "line": 19,
          "column": 16
        },
        "end": {
          "line": 19,
          "column": 25
        }
      }
    },
    {
      "type": {
        "label": "(",
        "beforeExpr": true,
        "startsExpr": true,
        "rightAssociative": false,
        "isLoop": false,
        "isAssign": false,
        "prefix": false,
        "postfix": false,
        "binop": null
      },
      "start": 697,
      "end": 698,
      "loc": {
        "start": {
          "line": 19,
          "column": 25
        },
        "end": {
          "line": 19,
          "column": 26
        }
      }
    },
    {
      "type": {
        "label": "name",
        "beforeExpr": false,
        "startsExpr": true,
        "rightAssociative": false,
        "isLoop": false,
        "isAssign": false,
        "prefix": false,
        "postfix": false,
        "binop": null
      },
      "value": "raw",
      "start": 698,
      "end": 701,
      "loc": {
        "start": {
          "line": 19,
          "column": 26
        },
        "end": {
          "line": 19,
          "column": 29
        }
      }
    },
    {
      "type": {
        "label": ",",
        "beforeExpr": true,
        "startsExpr": false,
        "rightAssociative": false,
        "isLoop": false,
        "isAssign": false,
        "prefix": false,
        "postfix": false,
        "binop": null,
        "updateContext": null
      },
      "start": 701,
      "end": 702,
      "loc": {
        "start": {
          "line": 19,
          "column": 29
        },
        "end": {
          "line": 19,
          "column": 30
        }
      }
    },
    {
      "type": {
        "label": "name",
        "beforeExpr": false,
        "startsExpr": true,
        "rightAssociative": false,
        "isLoop": false,
        "isAssign": false,
        "prefix": false,
        "postfix": false,
        "binop": null
      },
      "value": "args",
      "start": 703,
      "end": 707,
      "loc": {
        "start": {
          "line": 19,
          "column": 31
        },
        "end": {
          "line": 19,
          "column": 35
        }
      }
    },
    {
      "type": {
        "label": ")",
        "beforeExpr": false,
        "startsExpr": false,
        "rightAssociative": false,
        "isLoop": false,
        "isAssign": false,
        "prefix": false,
        "postfix": false,
        "binop": null
      },
      "start": 707,
      "end": 708,
      "loc": {
        "start": {
          "line": 19,
          "column": 35
        },
        "end": {
          "line": 19,
          "column": 36
        }
      }
    },
    {
      "type": {
        "label": "{",
        "beforeExpr": true,
        "startsExpr": true,
        "rightAssociative": false,
        "isLoop": false,
        "isAssign": false,
        "prefix": false,
        "postfix": false,
        "binop": null
      },
      "start": 709,
      "end": 710,
      "loc": {
        "start": {
          "line": 19,
          "column": 37
        },
        "end": {
          "line": 19,
          "column": 38
        }
      }
    },
    {
      "type": "CommentLine",
      "value": " raw response",
      "start": 714,
      "end": 729,
      "loc": {
        "start": {
          "line": 20,
          "column": 2
        },
        "end": {
          "line": 20,
          "column": 17
        }
      }
    },
    {
      "type": {
        "label": "name",
        "beforeExpr": false,
        "startsExpr": true,
        "rightAssociative": false,
        "isLoop": false,
        "isAssign": false,
        "prefix": false,
        "postfix": false,
        "binop": null
      },
      "value": "raw",
      "start": 733,
      "end": 736,
      "loc": {
        "start": {
          "line": 21,
          "column": 2
        },
        "end": {
          "line": 21,
          "column": 5
        }
      }
    },
    {
      "type": {
        "label": "=",
        "beforeExpr": true,
        "startsExpr": false,
        "rightAssociative": false,
        "isLoop": false,
        "isAssign": true,
        "prefix": false,
        "postfix": false,
        "binop": null,
        "updateContext": null
      },
      "value": "=",
      "start": 737,
      "end": 738,
      "loc": {
        "start": {
          "line": 21,
          "column": 6
        },
        "end": {
          "line": 21,
          "column": 7
        }
      }
    },
    {
      "type": {
        "label": "name",
        "beforeExpr": false,
        "startsExpr": true,
        "rightAssociative": false,
        "isLoop": false,
        "isAssign": false,
        "prefix": false,
        "postfix": false,
        "binop": null
      },
      "value": "raw",
      "start": 739,
      "end": 742,
      "loc": {
        "start": {
          "line": 21,
          "column": 8
        },
        "end": {
          "line": 21,
          "column": 11
        }
      }
    },
    {
      "type": {
        "label": ".",
        "beforeExpr": false,
        "startsExpr": false,
        "rightAssociative": false,
        "isLoop": false,
        "isAssign": false,
        "prefix": false,
        "postfix": false,
        "binop": null,
        "updateContext": null
      },
      "start": 742,
      "end": 743,
      "loc": {
        "start": {
          "line": 21,
          "column": 11
        },
        "end": {
          "line": 21,
          "column": 12
        }
      }
    },
    {
      "type": {
        "label": "name",
        "beforeExpr": false,
        "startsExpr": true,
        "rightAssociative": false,
        "isLoop": false,
        "isAssign": false,
        "prefix": false,
        "postfix": false,
        "binop": null
      },
      "value": "trim",
      "start": 743,
      "end": 747,
      "loc": {
        "start": {
          "line": 21,
          "column": 12
        },
        "end": {
          "line": 21,
          "column": 16
        }
      }
    },
    {
      "type": {
        "label": "(",
        "beforeExpr": true,
        "startsExpr": true,
        "rightAssociative": false,
        "isLoop": false,
        "isAssign": false,
        "prefix": false,
        "postfix": false,
        "binop": null
      },
      "start": 747,
      "end": 748,
      "loc": {
        "start": {
          "line": 21,
          "column": 16
        },
        "end": {
          "line": 21,
          "column": 17
        }
      }
    },
    {
      "type": {
        "label": ")",
        "beforeExpr": false,
        "startsExpr": false,
        "rightAssociative": false,
        "isLoop": false,
        "isAssign": false,
        "prefix": false,
        "postfix": false,
        "binop": null
      },
      "start": 748,
      "end": 749,
      "loc": {
        "start": {
          "line": 21,
          "column": 17
        },
        "end": {
          "line": 21,
          "column": 18
        }
      }
    },
    {
      "type": {
        "label": "if",
        "keyword": "if",
        "beforeExpr": false,
        "startsExpr": false,
        "rightAssociative": false,
        "isLoop": false,
        "isAssign": false,
        "prefix": false,
        "postfix": false,
        "binop": null,
        "updateContext": null
      },
      "value": "if",
      "start": 755,
      "end": 757,
      "loc": {
        "start": {
          "line": 23,
          "column": 2
        },
        "end": {
          "line": 23,
          "column": 4
        }
      }
    },
    {
      "type": {
        "label": "(",
        "beforeExpr": true,
        "startsExpr": true,
        "rightAssociative": false,
        "isLoop": false,
        "isAssign": false,
        "prefix": false,
        "postfix": false,
        "binop": null
      },
      "start": 758,
      "end": 759,
      "loc": {
        "start": {
          "line": 23,
          "column": 5
        },
        "end": {
          "line": 23,
          "column": 6
        }
      }
    },
    {
      "type": {
        "label": "name",
        "beforeExpr": false,
        "startsExpr": true,
        "rightAssociative": false,
        "isLoop": false,
        "isAssign": false,
        "prefix": false,
        "postfix": false,
        "binop": null
      },
      "value": "raw",
      "start": 759,
      "end": 762,
      "loc": {
        "start": {
          "line": 23,
          "column": 6
        },
        "end": {
          "line": 23,
          "column": 9
        }
      }
    },
    {
      "type": {
        "label": ".",
        "beforeExpr": false,
        "startsExpr": false,
        "rightAssociative": false,
        "isLoop": false,
        "isAssign": false,
        "prefix": false,
        "postfix": false,
        "binop": null,
        "updateContext": null
      },
      "start": 762,
      "end": 763,
      "loc": {
        "start": {
          "line": 23,
          "column": 9
        },
        "end": {
          "line": 23,
          "column": 10
        }
      }
    },
    {
      "type": {
        "label": "name",
        "beforeExpr": false,
        "startsExpr": true,
        "rightAssociative": false,
        "isLoop": false,
        "isAssign": false,
        "prefix": false,
        "postfix": false,
        "binop": null
      },
      "value": "startsWith",
      "start": 763,
      "end": 773,
      "loc": {
        "start": {
          "line": 23,
          "column": 10
        },
        "end": {
          "line": 23,
          "column": 20
        }
      }
    },
    {
      "type": {
        "label": "(",
        "beforeExpr": true,
        "startsExpr": true,
        "rightAssociative": false,
        "isLoop": false,
        "isAssign": false,
        "prefix": false,
        "postfix": false,
        "binop": null
      },
      "start": 773,
      "end": 774,
      "loc": {
        "start": {
          "line": 23,
          "column": 20
        },
        "end": {
          "line": 23,
          "column": 21
        }
      }
    },
    {
      "type": {
        "label": "string",
        "beforeExpr": false,
        "startsExpr": true,
        "rightAssociative": false,
        "isLoop": false,
        "isAssign": false,
        "prefix": false,
        "postfix": false,
        "binop": null,
        "updateContext": null
      },
      "value": "Not currently playing",
      "start": 774,
      "end": 797,
      "loc": {
        "start": {
          "line": 23,
          "column": 21
        },
        "end": {
          "line": 23,
          "column": 44
        }
      }
    },
    {
      "type": {
        "label": ")",
        "beforeExpr": false,
        "startsExpr": false,
        "rightAssociative": false,
        "isLoop": false,
        "isAssign": false,
        "prefix": false,
        "postfix": false,
        "binop": null
      },
      "start": 797,
      "end": 798,
      "loc": {
        "start": {
          "line": 23,
          "column": 44
        },
        "end": {
          "line": 23,
          "column": 45
        }
      }
    },
    {
      "type": {
        "label": ")",
        "beforeExpr": false,
        "startsExpr": false,
        "rightAssociative": false,
        "isLoop": false,
        "isAssign": false,
        "prefix": false,
        "postfix": false,
        "binop": null
      },
      "start": 798,
      "end": 799,
      "loc": {
        "start": {
          "line": 23,
          "column": 45
        },
        "end": {
          "line": 23,
          "column": 46
        }
      }
    },
    {
      "type": {
        "label": "{",
        "beforeExpr": true,
        "startsExpr": true,
        "rightAssociative": false,
        "isLoop": false,
        "isAssign": false,
        "prefix": false,
        "postfix": false,
        "binop": null
      },
      "start": 800,
      "end": 801,
      "loc": {
        "start": {
          "line": 23,
          "column": 47
        },
        "end": {
          "line": 23,
          "column": 48
        }
      }
    },
    {
      "type": {
        "label": "return",
        "keyword": "return",
        "beforeExpr": true,
        "startsExpr": false,
        "rightAssociative": false,
        "isLoop": false,
        "isAssign": false,
        "prefix": false,
        "postfix": false,
        "binop": null,
        "updateContext": null
      },
      "value": "return",
      "start": 807,
      "end": 813,
      "loc": {
        "start": {
          "line": 24,
          "column": 4
        },
        "end": {
          "line": 24,
          "column": 10
        }
      }
    },
    {
      "type": {
        "label": "new",
        "keyword": "new",
        "beforeExpr": true,
        "startsExpr": true,
        "rightAssociative": false,
        "isLoop": false,
        "isAssign": false,
        "prefix": false,
        "postfix": false,
        "binop": null,
        "updateContext": null
      },
      "value": "new",
      "start": 814,
      "end": 817,
      "loc": {
        "start": {
          "line": 24,
          "column": 11
        },
        "end": {
          "line": 24,
          "column": 14
        }
      }
    },
    {
      "type": {
        "label": "name",
        "beforeExpr": false,
        "startsExpr": true,
        "rightAssociative": false,
        "isLoop": false,
        "isAssign": false,
        "prefix": false,
        "postfix": false,
        "binop": null
      },
      "value": "Error",
      "start": 818,
      "end": 823,
      "loc": {
        "start": {
          "line": 24,
          "column": 15
        },
        "end": {
          "line": 24,
          "column": 20
        }
      }
    },
    {
      "type": {
        "label": "(",
        "beforeExpr": true,
        "startsExpr": true,
        "rightAssociative": false,
        "isLoop": false,
        "isAssign": false,
        "prefix": false,
        "postfix": false,
        "binop": null
      },
      "start": 823,
      "end": 824,
      "loc": {
        "start": {
          "line": 24,
          "column": 20
        },
        "end": {
          "line": 24,
          "column": 21
        }
      }
    },
    {
      "type": {
        "label": "string",
        "beforeExpr": false,
        "startsExpr": true,
        "rightAssociative": false,
        "isLoop": false,
        "isAssign": false,
        "prefix": false,
        "postfix": false,
        "binop": null,
        "updateContext": null
      },
      "value": "Not currently playing.",
      "start": 824,
      "end": 848,
      "loc": {
        "start": {
          "line": 24,
          "column": 21
        },
        "end": {
          "line": 24,
          "column": 45
        }
      }
    },
    {
      "type": {
        "label": ")",
        "beforeExpr": false,
        "startsExpr": false,
        "rightAssociative": false,
        "isLoop": false,
        "isAssign": false,
        "prefix": false,
        "postfix": false,
        "binop": null
      },
      "start": 848,
      "end": 849,
      "loc": {
        "start": {
          "line": 24,
          "column": 45
        },
        "end": {
          "line": 24,
          "column": 46
        }
      }
    },
    {
      "type": {
        "label": "}",
        "beforeExpr": false,
        "startsExpr": false,
        "rightAssociative": false,
        "isLoop": false,
        "isAssign": false,
        "prefix": false,
        "postfix": false,
        "binop": null
      },
      "start": 853,
      "end": 854,
      "loc": {
        "start": {
          "line": 25,
          "column": 2
        },
        "end": {
          "line": 25,
          "column": 3
        }
      }
    },
    {
      "type": {
        "label": "if",
        "keyword": "if",
        "beforeExpr": false,
        "startsExpr": false,
        "rightAssociative": false,
        "isLoop": false,
        "isAssign": false,
        "prefix": false,
        "postfix": false,
        "binop": null,
        "updateContext": null
      },
      "value": "if",
      "start": 860,
      "end": 862,
      "loc": {
        "start": {
          "line": 27,
          "column": 2
        },
        "end": {
          "line": 27,
          "column": 4
        }
      }
    },
    {
      "type": {
        "label": "(",
        "beforeExpr": true,
        "startsExpr": true,
        "rightAssociative": false,
        "isLoop": false,
        "isAssign": false,
        "prefix": false,
        "postfix": false,
        "binop": null
      },
      "start": 863,
      "end": 864,
      "loc": {
        "start": {
          "line": 27,
          "column": 5
        },
        "end": {
          "line": 27,
          "column": 6
        }
      }
    },
    {
      "type": {
        "label": "prefix",
        "beforeExpr": true,
        "startsExpr": true,
        "rightAssociative": false,
        "isLoop": false,
        "isAssign": false,
        "prefix": true,
        "postfix": false,
        "binop": null,
        "updateContext": null
      },
      "value": "!",
      "start": 864,
      "end": 865,
      "loc": {
        "start": {
          "line": 27,
          "column": 6
        },
        "end": {
          "line": 27,
          "column": 7
        }
      }
    },
    {
      "type": {
        "label": "name",
        "beforeExpr": false,
        "startsExpr": true,
        "rightAssociative": false,
        "isLoop": false,
        "isAssign": false,
        "prefix": false,
        "postfix": false,
        "binop": null
      },
      "value": "raw",
      "start": 866,
      "end": 869,
      "loc": {
        "start": {
          "line": 27,
          "column": 8
        },
        "end": {
          "line": 27,
          "column": 11
        }
      }
    },
    {
      "type": {
        "label": ".",
        "beforeExpr": false,
        "startsExpr": false,
        "rightAssociative": false,
        "isLoop": false,
        "isAssign": false,
        "prefix": false,
        "postfix": false,
        "binop": null,
        "updateContext": null
      },
      "start": 869,
      "end": 870,
      "loc": {
        "start": {
          "line": 27,
          "column": 11
        },
        "end": {
          "line": 27,
          "column": 12
        }
      }
    },
    {
      "type": {
        "label": "name",
        "beforeExpr": false,
        "startsExpr": true,
        "rightAssociative": false,
        "isLoop": false,
        "isAssign": false,
        "prefix": false,
        "postfix": false,
        "binop": null
      },
      "value": "startsWith",
      "start": 870,
      "end": 880,
      "loc": {
        "start": {
          "line": 27,
          "column": 12
        },
        "end": {
          "line": 27,
          "column": 22
        }
      }
    },
    {
      "type": {
        "label": "(",
        "beforeExpr": true,
        "startsExpr": true,
        "rightAssociative": false,
        "isLoop": false,
        "isAssign": false,
        "prefix": false,
        "postfix": false,
        "binop": null
      },
      "start": 880,
      "end": 881,
      "loc": {
        "start": {
          "line": 27,
          "column": 22
        },
        "end": {
          "line": 27,
          "column": 23
        }
      }
    },
    {
      "type": {
        "label": "string",
        "beforeExpr": false,
        "startsExpr": true,
        "rightAssociative": false,
        "isLoop": false,
        "isAssign": false,
        "prefix": false,
        "postfix": false,
        "binop": null,
        "updateContext": null
      },
      "value": "Aborted playing or paused file",
      "start": 881,
      "end": 913,
      "loc": {
        "start": {
          "line": 27,
          "column": 23
        },
        "end": {
          "line": 27,
          "column": 55
        }
      }
    },
    {
      "type": {
        "label": ")",
        "beforeExpr": false,
        "startsExpr": false,
        "rightAssociative": false,
        "isLoop": false,
        "isAssign": false,
        "prefix": false,
        "postfix": false,
        "binop": null
      },
      "start": 913,
      "end": 914,
      "loc": {
        "start": {
          "line": 27,
          "column": 55
        },
        "end": {
          "line": 27,
          "column": 56
        }
      }
    },
    {
      "type": {
        "label": ")",
        "beforeExpr": false,
        "startsExpr": false,
        "rightAssociative": false,
        "isLoop": false,
        "isAssign": false,
        "prefix": false,
        "postfix": false,
        "binop": null
      },
      "start": 914,
      "end": 915,
      "loc": {
        "start": {
          "line": 27,
          "column": 56
        },
        "end": {
          "line": 27,
          "column": 57
        }
      }
    },
    {
      "type": {
        "label": "{",
        "beforeExpr": true,
        "startsExpr": true,
        "rightAssociative": false,
        "isLoop": false,
        "isAssign": false,
        "prefix": false,
        "postfix": false,
        "binop": null
      },
      "start": 916,
      "end": 917,
      "loc": {
        "start": {
          "line": 27,
          "column": 58
        },
        "end": {
          "line": 27,
          "column": 59
        }
      }
    },
    {
      "type": {
        "label": "return",
        "keyword": "return",
        "beforeExpr": true,
        "startsExpr": false,
        "rightAssociative": false,
        "isLoop": false,
        "isAssign": false,
        "prefix": false,
        "postfix": false,
        "binop": null,
        "updateContext": null
      },
      "value": "return",
      "start": 923,
      "end": 929,
      "loc": {
        "start": {
          "line": 28,
          "column": 4
        },
        "end": {
          "line": 28,
          "column": 10
        }
      }
    },
    {
      "type": {
        "label": "new",
        "keyword": "new",
        "beforeExpr": true,
        "startsExpr": true,
        "rightAssociative": false,
        "isLoop": false,
        "isAssign": false,
        "prefix": false,
        "postfix": false,
        "binop": null,
        "updateContext": null
      },
      "value": "new",
      "start": 930,
      "end": 933,
      "loc": {
        "start": {
          "line": 28,
          "column": 11
        },
        "end": {
          "line": 28,
          "column": 14
        }
      }
    },
    {
      "type": {
        "label": "name",
        "beforeExpr": false,
        "startsExpr": true,
        "rightAssociative": false,
        "isLoop": false,
        "isAssign": false,
        "prefix": false,
        "postfix": false,
        "binop": null
      },
      "value": "Error",
      "start": 934,
      "end": 939,
      "loc": {
        "start": {
          "line": 28,
          "column": 15
        },
        "end": {
          "line": 28,
          "column": 20
        }
      }
    },
    {
      "type": {
        "label": "(",
        "beforeExpr": true,
        "startsExpr": true,
        "rightAssociative": false,
        "isLoop": false,
        "isAssign": false,
        "prefix": false,
        "postfix": false,
        "binop": null
      },
      "start": 939,
      "end": 940,
      "loc": {
        "start": {
          "line": 28,
          "column": 20
        },
        "end": {
          "line": 28,
          "column": 21
        }
      }
    },
    {
      "type": {
        "label": "string",
        "beforeExpr": false,
        "startsExpr": true,
        "rightAssociative": false,
        "isLoop": false,
        "isAssign": false,
        "prefix": false,
        "postfix": false,
        "binop": null,
        "updateContext": null
      },
      "value": "Unknown response string.",
      "start": 940,
      "end": 966,
      "loc": {
        "start": {
          "line": 28,
          "column": 21
        },
        "end": {
          "line": 28,
          "column": 47
        }
      }
    },
    {
      "type": {
        "label": ")",
        "beforeExpr": false,
        "startsExpr": false,
        "rightAssociative": false,
        "isLoop": false,
        "isAssign": false,
        "prefix": false,
        "postfix": false,
        "binop": null
      },
      "start": 966,
      "end": 967,
      "loc": {
        "start": {
          "line": 28,
          "column": 47
        },
        "end": {
          "line": 28,
          "column": 48
        }
      }
    },
    {
      "type": {
        "label": "}",
        "beforeExpr": false,
        "startsExpr": false,
        "rightAssociative": false,
        "isLoop": false,
        "isAssign": false,
        "prefix": false,
        "postfix": false,
        "binop": null
      },
      "start": 971,
      "end": 972,
      "loc": {
        "start": {
          "line": 29,
          "column": 2
        },
        "end": {
          "line": 29,
          "column": 3
        }
      }
    },
    {
      "type": {
        "label": "return",
        "keyword": "return",
        "beforeExpr": true,
        "startsExpr": false,
        "rightAssociative": false,
        "isLoop": false,
        "isAssign": false,
        "prefix": false,
        "postfix": false,
        "binop": null,
        "updateContext": null
      },
      "value": "return",
      "start": 978,
      "end": 984,
      "loc": {
        "start": {
          "line": 31,
          "column": 2
        },
        "end": {
          "line": 31,
          "column": 8
        }
      }
    },
    {
      "type": {
        "label": "string",
        "beforeExpr": false,
        "startsExpr": true,
        "rightAssociative": false,
        "isLoop": false,
        "isAssign": false,
        "prefix": false,
        "postfix": false,
        "binop": null,
        "updateContext": null
      },
      "value": "Aborted! Please turn any heaters off manually.",
      "start": 985,
      "end": 1033,
      "loc": {
        "start": {
          "line": 31,
          "column": 9
        },
        "end": {
          "line": 31,
          "column": 57
        }
      }
    },
    {
      "type": {
        "label": "}",
        "beforeExpr": false,
        "startsExpr": false,
        "rightAssociative": false,
        "isLoop": false,
        "isAssign": false,
        "prefix": false,
        "postfix": false,
        "binop": null
      },
      "start": 1035,
      "end": 1036,
      "loc": {
        "start": {
          "line": 32,
          "column": 0
        },
        "end": {
          "line": 32,
          "column": 1
        }
      }
    },
    {
      "type": {
        "label": "eof",
        "beforeExpr": false,
        "startsExpr": false,
        "rightAssociative": false,
        "isLoop": false,
        "isAssign": false,
        "prefix": false,
        "postfix": false,
        "binop": null,
        "updateContext": null
      },
      "start": 1038,
      "end": 1038,
      "loc": {
        "start": {
          "line": 33,
          "column": 0
        },
        "end": {
          "line": 33,
          "column": 0
        }
      }
    }
  ]
}