{
  "type": "File",
  "start": 0,
  "end": 887,
  "loc": {
    "start": {
      "line": 1,
      "column": 0
    },
    "end": {
      "line": 39,
      "column": 0
    }
  },
  "program": {
    "type": "Program",
    "start": 0,
    "end": 887,
    "loc": {
      "start": {
        "line": 1,
        "column": 0
      },
      "end": {
        "line": 39,
        "column": 0
      }
    },
    "sourceType": "module",
    "body": [
      {
        "type": "ExportNamedDeclaration",
        "start": 498,
        "end": 886,
        "loc": {
          "start": {
            "line": 22,
            "column": 0
          },
          "end": {
            "line": 38,
            "column": 1
          }
        },
        "specifiers": [],
        "source": null,
        "declaration": {
          "type": "FunctionDeclaration",
          "start": 505,
          "end": 886,
          "loc": {
            "start": {
              "line": 22,
              "column": 7
            },
            "end": {
              "line": 38,
              "column": 1
            }
          },
          "id": {
            "type": "Identifier",
            "start": 514,
            "end": 526,
            "loc": {
              "start": {
                "line": 22,
                "column": 16
              },
              "end": {
                "line": 22,
                "column": 28
              },
              "identifierName": "cmd_set_temp"
            },
            "name": "cmd_set_temp",
            "leadingComments": null
          },
          "generator": false,
          "expression": false,
          "async": false,
          "params": [
            {
              "type": "Identifier",
              "start": 527,
              "end": 530,
              "loc": {
                "start": {
                  "line": 22,
                  "column": 29
                },
                "end": {
                  "line": 22,
                  "column": 32
                },
                "identifierName": "raw"
              },
              "name": "raw"
            },
            {
              "type": "Identifier",
              "start": 532,
              "end": 536,
              "loc": {
                "start": {
                  "line": 22,
                  "column": 34
                },
                "end": {
                  "line": 22,
                  "column": 38
                },
                "identifierName": "args"
              },
              "name": "args"
            }
          ],
          "body": {
            "type": "BlockStatement",
            "start": 538,
            "end": 886,
            "loc": {
              "start": {
                "line": 22,
                "column": 40
              },
              "end": {
                "line": 38,
                "column": 1
              }
            },
            "body": [
              {
                "type": "ExpressionStatement",
                "start": 560,
                "end": 576,
                "loc": {
                  "start": {
                    "line": 24,
                    "column": 2
                  },
                  "end": {
                    "line": 24,
                    "column": 18
                  }
                },
                "expression": {
                  "type": "AssignmentExpression",
                  "start": 560,
                  "end": 576,
                  "loc": {
                    "start": {
                      "line": 24,
                      "column": 2
                    },
                    "end": {
                      "line": 24,
                      "column": 18
                    }
                  },
                  "operator": "=",
                  "left": {
                    "type": "Identifier",
                    "start": 560,
                    "end": 563,
                    "loc": {
                      "start": {
                        "line": 24,
                        "column": 2
                      },
                      "end": {
                        "line": 24,
                        "column": 5
                      },
                      "identifierName": "raw"
                    },
                    "name": "raw",
                    "leadingComments": null
                  },
                  "right": {
                    "type": "CallExpression",
                    "start": 566,
                    "end": 576,
                    "loc": {
                      "start": {
                        "line": 24,
                        "column": 8
                      },
                      "end": {
                        "line": 24,
                        "column": 18
                      }
                    },
                    "callee": {
                      "type": "MemberExpression",
                      "start": 566,
                      "end": 574,
                      "loc": {
                        "start": {
                          "line": 24,
                          "column": 8
                        },
                        "end": {
                          "line": 24,
                          "column": 16
                        }
                      },
                      "object": {
                        "type": "Identifier",
                        "start": 566,
                        "end": 569,
                        "loc": {
                          "start": {
                            "line": 24,
                            "column": 8
                          },
                          "end": {
                            "line": 24,
                            "column": 11
                          },
                          "identifierName": "raw"
                        },
                        "name": "raw"
                      },
                      "property": {
                        "type": "Identifier",
                        "start": 570,
                        "end": 574,
                        "loc": {
                          "start": {
                            "line": 24,
                            "column": 12
                          },
                          "end": {
                            "line": 24,
                            "column": 16
                          },
                          "identifierName": "trim"
                        },
                        "name": "trim"
                      },
                      "computed": false
                    },
                    "arguments": [],
                    "trailingComments": null
                  },
                  "leadingComments": null,
                  "trailingComments": null
                },
                "leadingComments": [
                  {
                    "type": "CommentLine",
                    "value": " raw response",
                    "start": 542,
                    "end": 557,
                    "loc": {
                      "start": {
                        "line": 23,
                        "column": 2
                      },
                      "end": {
                        "line": 23,
                        "column": 17
                      }
                    }
                  }
                ],
                "trailingComments": [
                  {
                    "type": "CommentLine",
                    "value": " device",
                    "start": 580,
                    "end": 589,
                    "loc": {
                      "start": {
                        "line": 26,
                        "column": 2
                      },
                      "end": {
                        "line": 26,
                        "column": 11
                      }
                    }
                  }
                ]
              },
              {
                "type": "VariableDeclaration",
                "start": 592,
                "end": 639,
                "loc": {
                  "start": {
                    "line": 27,
                    "column": 2
                  },
                  "end": {
                    "line": 27,
                    "column": 49
                  }
                },
                "declarations": [
                  {
                    "type": "VariableDeclarator",
                    "start": 596,
                    "end": 639,
                    "loc": {
                      "start": {
                        "line": 27,
                        "column": 6
                      },
                      "end": {
                        "line": 27,
                        "column": 49
                      }
                    },
                    "id": {
                      "type": "Identifier",
                      "start": 596,
                      "end": 602,
                      "loc": {
                        "start": {
                          "line": 27,
                          "column": 6
                        },
                        "end": {
                          "line": 27,
                          "column": 12
                        },
                        "identifierName": "device"
                      },
                      "name": "device",
                      "leadingComments": null
                    },
                    "init": {
                      "type": "CallExpression",
                      "start": 605,
                      "end": 639,
                      "loc": {
                        "start": {
                          "line": 27,
                          "column": 15
                        },
                        "end": {
                          "line": 27,
                          "column": 49
                        }
                      },
                      "callee": {
                        "type": "MemberExpression",
                        "start": 605,
                        "end": 637,
                        "loc": {
                          "start": {
                            "line": 27,
                            "column": 15
                          },
                          "end": {
                            "line": 27,
                            "column": 47
                          }
                        },
                        "object": {
                          "type": "LogicalExpression",
                          "start": 606,
                          "end": 624,
                          "loc": {
                            "start": {
                              "line": 27,
                              "column": 16
                            },
                            "end": {
                              "line": 27,
                              "column": 34
                            }
                          },
                          "left": {
                            "type": "CallExpression",
                            "start": 606,
                            "end": 618,
                            "loc": {
                              "start": {
                                "line": 27,
                                "column": 16
                              },
                              "end": {
                                "line": 27,
                                "column": 28
                              }
                            },
                            "callee": {
                              "type": "MemberExpression",
                              "start": 606,
                              "end": 616,
                              "loc": {
                                "start": {
                                  "line": 27,
                                  "column": 16
                                },
                                "end": {
                                  "line": 27,
                                  "column": 26
                                }
                              },
                              "object": {
                                "type": "Identifier",
                                "start": 606,
                                "end": 610,
                                "loc": {
                                  "start": {
                                    "line": 27,
                                    "column": 16
                                  },
                                  "end": {
                                    "line": 27,
                                    "column": 20
                                  },
                                  "identifierName": "args"
                                },
                                "name": "args"
                              },
                              "property": {
                                "type": "Identifier",
                                "start": 611,
                                "end": 616,
                                "loc": {
                                  "start": {
                                    "line": 27,
                                    "column": 21
                                  },
                                  "end": {
                                    "line": 27,
                                    "column": 26
                                  },
                                  "identifierName": "shift"
                                },
                                "name": "shift"
                              },
                              "computed": false
                            },
                            "arguments": []
                          },
                          "operator": "||",
                          "right": {
                            "type": "StringLiteral",
                            "start": 622,
                            "end": 624,
                            "loc": {
                              "start": {
                                "line": 27,
                                "column": 32
                              },
                              "end": {
                                "line": 27,
                                "column": 34
                              }
                            },
                            "extra": {
                              "rawValue": "",
                              "raw": "''"
                            },
                            "value": ""
                          },
                          "extra": {
                            "parenthesized": true,
                            "parenStart": 605
                          }
                        },
                        "property": {
                          "type": "Identifier",
                          "start": 626,
                          "end": 637,
                          "loc": {
                            "start": {
                              "line": 27,
                              "column": 36
                            },
                            "end": {
                              "line": 27,
                              "column": 47
                            },
                            "identifierName": "toLowerCase"
                          },
                          "name": "toLowerCase"
                        },
                        "computed": false
                      },
                      "arguments": [],
                      "trailingComments": null
                    },
                    "leadingComments": null,
                    "trailingComments": null
                  }
                ],
                "kind": "let",
                "leadingComments": [
                  {
                    "type": "CommentLine",
                    "value": " device",
                    "start": 580,
                    "end": 589,
                    "loc": {
                      "start": {
                        "line": 26,
                        "column": 2
                      },
                      "end": {
                        "line": 26,
                        "column": 11
                      }
                    }
                  }
                ],
                "trailingComments": [
                  {
                    "type": "CommentLine",
                    "value": " error",
                    "start": 643,
                    "end": 651,
                    "loc": {
                      "start": {
                        "line": 29,
                        "column": 2
                      },
                      "end": {
                        "line": 29,
                        "column": 10
                      }
                    }
                  }
                ]
              },
              {
                "type": "IfStatement",
                "start": 654,
                "end": 790,
                "loc": {
                  "start": {
                    "line": 30,
                    "column": 2
                  },
                  "end": {
                    "line": 32,
                    "column": 3
                  }
                },
                "test": {
                  "type": "CallExpression",
                  "start": 658,
                  "end": 707,
                  "loc": {
                    "start": {
                      "line": 30,
                      "column": 6
                    },
                    "end": {
                      "line": 30,
                      "column": 55
                    }
                  },
                  "callee": {
                    "type": "MemberExpression",
                    "start": 658,
                    "end": 670,
                    "loc": {
                      "start": {
                        "line": 30,
                        "column": 6
                      },
                      "end": {
                        "line": 30,
                        "column": 18
                      }
                    },
                    "object": {
                      "type": "Identifier",
                      "start": 658,
                      "end": 661,
                      "loc": {
                        "start": {
                          "line": 30,
                          "column": 6
                        },
                        "end": {
                          "line": 30,
                          "column": 9
                        },
                        "identifierName": "raw"
                      },
                      "name": "raw",
                      "leadingComments": null
                    },
                    "property": {
                      "type": "Identifier",
                      "start": 662,
                      "end": 670,
                      "loc": {
                        "start": {
                          "line": 30,
                          "column": 10
                        },
                        "end": {
                          "line": 30,
                          "column": 18
                        },
                        "identifierName": "endsWith"
                      },
                      "name": "endsWith"
                    },
                    "computed": false,
                    "leadingComments": null
                  },
                  "arguments": [
                    {
                      "type": "StringLiteral",
                      "start": 671,
                      "end": 706,
                      "loc": {
                        "start": {
                          "line": 30,
                          "column": 19
                        },
                        "end": {
                          "line": 30,
                          "column": 54
                        }
                      },
                      "extra": {
                        "rawValue": "is not a known temperature device",
                        "raw": "'is not a known temperature device'"
                      },
                      "value": "is not a known temperature device"
                    }
                  ],
                  "leadingComments": null
                },
                "consequent": {
                  "type": "BlockStatement",
                  "start": 709,
                  "end": 790,
                  "loc": {
                    "start": {
                      "line": 30,
                      "column": 57
                    },
                    "end": {
                      "line": 32,
                      "column": 3
                    }
                  },
                  "body": [
                    {
                      "type": "ReturnStatement",
                      "start": 715,
                      "end": 786,
                      "loc": {
                        "start": {
                          "line": 31,
                          "column": 4
                        },
                        "end": {
                          "line": 31,
                          "column": 75
                        }
                      },
                      "argument": {
                        "type": "NewExpression",
                        "start": 722,
                        "end": 786,
                        "loc": {
                          "start": {
                            "line": 31,
                            "column": 11
                          },
                          "end": {
                            "line": 31,
                            "column": 75
                          }
                        },
                        "callee": {
                          "type": "Identifier",
                          "start": 726,
                          "end": 731,
                          "loc": {
                            "start": {
                              "line": 31,
                              "column": 15
                            },
                            "end": {
                              "line": 31,
                              "column": 20
                            },
                            "identifierName": "Error"
                          },
                          "name": "Error"
                        },
                        "arguments": [
                          {
                            "type": "BinaryExpression",
                            "start": 732,
                            "end": 785,
                            "loc": {
                              "start": {
                                "line": 31,
                                "column": 21
                              },
                              "end": {
                                "line": 31,
                                "column": 74
                              }
                            },
                            "left": {
                              "type": "BinaryExpression",
                              "start": 732,
                              "end": 744,
                              "loc": {
                                "start": {
                                  "line": 31,
                                  "column": 21
                                },
                                "end": {
                                  "line": 31,
                                  "column": 33
                                }
                              },
                              "left": {
                                "type": "StringLiteral",
                                "start": 732,
                                "end": 735,
                                "loc": {
                                  "start": {
                                    "line": 31,
                                    "column": 21
                                  },
                                  "end": {
                                    "line": 31,
                                    "column": 24
                                  }
                                },
                                "extra": {
                                  "rawValue": "\"",
                                  "raw": "'\"'"
                                },
                                "value": "\""
                              },
                              "operator": "+",
                              "right": {
                                "type": "Identifier",
                                "start": 738,
                                "end": 744,
                                "loc": {
                                  "start": {
                                    "line": 31,
                                    "column": 27
                                  },
                                  "end": {
                                    "line": 31,
                                    "column": 33
                                  },
                                  "identifierName": "device"
                                },
                                "name": "device"
                              }
                            },
                            "operator": "+",
                            "right": {
                              "type": "StringLiteral",
                              "start": 747,
                              "end": 785,
                              "loc": {
                                "start": {
                                  "line": 31,
                                  "column": 36
                                },
                                "end": {
                                  "line": 31,
                                  "column": 74
                                }
                              },
                              "extra": {
                                "rawValue": "\" is not a known temperature device.",
                                "raw": "'\" is not a known temperature device.'"
                              },
                              "value": "\" is not a known temperature device."
                            }
                          }
                        ]
                      }
                    }
                  ],
                  "directives": [],
                  "trailingComments": null
                },
                "alternate": null,
                "leadingComments": [
                  {
                    "type": "CommentLine",
                    "value": " error",
                    "start": 643,
                    "end": 651,
                    "loc": {
                      "start": {
                        "line": 29,
                        "column": 2
                      },
                      "end": {
                        "line": 29,
                        "column": 10
                      }
                    }
                  }
                ],
                "trailingComments": [
                  {
                    "type": "CommentLine",
                    "value": " new temperature",
                    "start": 794,
                    "end": 812,
                    "loc": {
                      "start": {
                        "line": 34,
                        "column": 2
                      },
                      "end": {
                        "line": 34,
                        "column": 20
                      }
                    }
                  }
                ]
              },
              {
                "type": "VariableDeclaration",
                "start": 815,
                "end": 855,
                "loc": {
                  "start": {
                    "line": 35,
                    "column": 2
                  },
                  "end": {
                    "line": 35,
                    "column": 42
                  }
                },
                "declarations": [
                  {
                    "type": "VariableDeclarator",
                    "start": 819,
                    "end": 855,
                    "loc": {
                      "start": {
                        "line": 35,
                        "column": 6
                      },
                      "end": {
                        "line": 35,
                        "column": 42
                      }
                    },
                    "id": {
                      "type": "Identifier",
                      "start": 819,
                      "end": 825,
                      "loc": {
                        "start": {
                          "line": 35,
                          "column": 6
                        },
                        "end": {
                          "line": 35,
                          "column": 12
                        },
                        "identifierName": "target"
                      },
                      "name": "target",
                      "leadingComments": null
                    },
                    "init": {
                      "type": "CallExpression",
                      "start": 828,
                      "end": 855,
                      "loc": {
                        "start": {
                          "line": 35,
                          "column": 15
                        },
                        "end": {
                          "line": 35,
                          "column": 42
                        }
                      },
                      "callee": {
                        "type": "Identifier",
                        "start": 828,
                        "end": 836,
                        "loc": {
                          "start": {
                            "line": 35,
                            "column": 15
                          },
                          "end": {
                            "line": 35,
                            "column": 23
                          },
                          "identifierName": "parseInt"
                        },
                        "name": "parseInt"
                      },
                      "arguments": [
                        {
                          "type": "LogicalExpression",
                          "start": 837,
                          "end": 854,
                          "loc": {
                            "start": {
                              "line": 35,
                              "column": 24
                            },
                            "end": {
                              "line": 35,
                              "column": 41
                            }
                          },
                          "left": {
                            "type": "CallExpression",
                            "start": 837,
                            "end": 849,
                            "loc": {
                              "start": {
                                "line": 35,
                                "column": 24
                              },
                              "end": {
                                "line": 35,
                                "column": 36
                              }
                            },
                            "callee": {
                              "type": "MemberExpression",
                              "start": 837,
                              "end": 847,
                              "loc": {
                                "start": {
                                  "line": 35,
                                  "column": 24
                                },
                                "end": {
                                  "line": 35,
                                  "column": 34
                                }
                              },
                              "object": {
                                "type": "Identifier",
                                "start": 837,
                                "end": 841,
                                "loc": {
                                  "start": {
                                    "line": 35,
                                    "column": 24
                                  },
                                  "end": {
                                    "line": 35,
                                    "column": 28
                                  },
                                  "identifierName": "args"
                                },
                                "name": "args"
                              },
                              "property": {
                                "type": "Identifier",
                                "start": 842,
                                "end": 847,
                                "loc": {
                                  "start": {
                                    "line": 35,
                                    "column": 29
                                  },
                                  "end": {
                                    "line": 35,
                                    "column": 34
                                  },
                                  "identifierName": "shift"
                                },
                                "name": "shift"
                              },
                              "computed": false
                            },
                            "arguments": []
                          },
                          "operator": "||",
                          "right": {
                            "type": "NumericLiteral",
                            "start": 853,
                            "end": 854,
                            "loc": {
                              "start": {
                                "line": 35,
                                "column": 40
                              },
                              "end": {
                                "line": 35,
                                "column": 41
                              }
                            },
                            "extra": {
                              "rawValue": 0,
                              "raw": "0"
                            },
                            "value": 0
                          }
                        }
                      ]
                    },
                    "leadingComments": null
                  }
                ],
                "kind": "let",
                "leadingComments": [
                  {
                    "type": "CommentLine",
                    "value": " new temperature",
                    "start": 794,
                    "end": 812,
                    "loc": {
                      "start": {
                        "line": 34,
                        "column": 2
                      },
                      "end": {
                        "line": 34,
                        "column": 20
                      }
                    }
                  }
                ]
              },
              {
                "type": "ReturnStatement",
                "start": 859,
                "end": 884,
                "loc": {
                  "start": {
                    "line": 37,
                    "column": 2
                  },
                  "end": {
                    "line": 37,
                    "column": 27
                  }
                },
                "argument": {
                  "type": "ObjectExpression",
                  "start": 866,
                  "end": 884,
                  "loc": {
                    "start": {
                      "line": 37,
                      "column": 9
                    },
                    "end": {
                      "line": 37,
                      "column": 27
                    }
                  },
                  "properties": [
                    {
                      "type": "ObjectProperty",
                      "start": 868,
                      "end": 874,
                      "loc": {
                        "start": {
                          "line": 37,
                          "column": 11
                        },
                        "end": {
                          "line": 37,
                          "column": 17
                        }
                      },
                      "method": false,
                      "shorthand": true,
                      "computed": false,
                      "key": {
                        "type": "Identifier",
                        "start": 868,
                        "end": 874,
                        "loc": {
                          "start": {
                            "line": 37,
                            "column": 11
                          },
                          "end": {
                            "line": 37,
                            "column": 17
                          },
                          "identifierName": "device"
                        },
                        "name": "device"
                      },
                      "value": {
                        "type": "Identifier",
                        "start": 868,
                        "end": 874,
                        "loc": {
                          "start": {
                            "line": 37,
                            "column": 11
                          },
                          "end": {
                            "line": 37,
                            "column": 17
                          },
                          "identifierName": "device"
                        },
                        "name": "device"
                      },
                      "extra": {
                        "shorthand": true
                      }
                    },
                    {
                      "type": "ObjectProperty",
                      "start": 876,
                      "end": 882,
                      "loc": {
                        "start": {
                          "line": 37,
                          "column": 19
                        },
                        "end": {
                          "line": 37,
                          "column": 25
                        }
                      },
                      "method": false,
                      "shorthand": true,
                      "computed": false,
                      "key": {
                        "type": "Identifier",
                        "start": 876,
                        "end": 882,
                        "loc": {
                          "start": {
                            "line": 37,
                            "column": 19
                          },
                          "end": {
                            "line": 37,
                            "column": 25
                          },
                          "identifierName": "target"
                        },
                        "name": "target"
                      },
                      "value": {
                        "type": "Identifier",
                        "start": 876,
                        "end": 882,
                        "loc": {
                          "start": {
                            "line": 37,
                            "column": 19
                          },
                          "end": {
                            "line": 37,
                            "column": 25
                          },
                          "identifierName": "target"
                        },
                        "name": "target"
                      },
                      "extra": {
                        "shorthand": true
                      }
                    }
                  ]
                }
              }
            ],
            "directives": []
          },
          "leadingComments": [
            {
              "type": "CommentBlock",
              "value": "*\n* Set temperature.\n*\n* - set_temp [bed|hotend]\n*\n* ### on success\n* ```\n* return {\n*   \"device\": \"bed\",\n*   \"target\": 180\n* }\n* ```\n* ### on error\n* ```\n* return Error: '\"xxx\" is not a known temperature device.'\n* ```\n* @param  {String}   raw  Raw command response string.\n* @param  {String[]} args Command arguments.\n* @return {Object|Error}\n* @see https://github.com/Smoothieware/Smoothieware/blob/d79254323f4bb951426c6add29a4451130eaa018/src/modules/utils/simpleshell/SimpleShell.cpp#857\n",
              "start": 0,
              "end": 497,
              "loc": {
                "start": {
                  "line": 1,
                  "column": 0
                },
                "end": {
                  "line": 21,
                  "column": 2
                }
              }
            }
          ],
          "trailingComments": []
        },
        "leadingComments": [
          {
            "type": "CommentBlock",
            "value": "*\n* Set temperature.\n*\n* - set_temp [bed|hotend]\n*\n* ### on success\n* ```\n* return {\n*   \"device\": \"bed\",\n*   \"target\": 180\n* }\n* ```\n* ### on error\n* ```\n* return Error: '\"xxx\" is not a known temperature device.'\n* ```\n* @param  {String}   raw  Raw command response string.\n* @param  {String[]} args Command arguments.\n* @return {Object|Error}\n* @see https://github.com/Smoothieware/Smoothieware/blob/d79254323f4bb951426c6add29a4451130eaa018/src/modules/utils/simpleshell/SimpleShell.cpp#857\n",
            "start": 0,
            "end": 497,
            "loc": {
              "start": {
                "line": 1,
                "column": 0
              },
              "end": {
                "line": 21,
                "column": 2
              }
            }
          }
        ]
      }
    ],
    "directives": []
  },
  "comments": [
    {
      "type": "CommentBlock",
      "value": "*\n* Set temperature.\n*\n* - set_temp [bed|hotend]\n*\n* ### on success\n* ```\n* return {\n*   \"device\": \"bed\",\n*   \"target\": 180\n* }\n* ```\n* ### on error\n* ```\n* return Error: '\"xxx\" is not a known temperature device.'\n* ```\n* @param  {String}   raw  Raw command response string.\n* @param  {String[]} args Command arguments.\n* @return {Object|Error}\n* @see https://github.com/Smoothieware/Smoothieware/blob/d79254323f4bb951426c6add29a4451130eaa018/src/modules/utils/simpleshell/SimpleShell.cpp#857\n",
      "start": 0,
      "end": 497,
      "loc": {
        "start": {
          "line": 1,
          "column": 0
        },
        "end": {
          "line": 21,
          "column": 2
        }
      }
    },
    {
      "type": "CommentLine",
      "value": " raw response",
      "start": 542,
      "end": 557,
      "loc": {
        "start": {
          "line": 23,
          "column": 2
        },
        "end": {
          "line": 23,
          "column": 17
        }
      }
    },
    {
      "type": "CommentLine",
      "value": " device",
      "start": 580,
      "end": 589,
      "loc": {
        "start": {
          "line": 26,
          "column": 2
        },
        "end": {
          "line": 26,
          "column": 11
        }
      }
    },
    {
      "type": "CommentLine",
      "value": " error",
      "start": 643,
      "end": 651,
      "loc": {
        "start": {
          "line": 29,
          "column": 2
        },
        "end": {
          "line": 29,
          "column": 10
        }
      }
    },
    {
      "type": "CommentLine",
      "value": " new temperature",
      "start": 794,
      "end": 812,
      "loc": {
        "start": {
          "line": 34,
          "column": 2
        },
        "end": {
          "line": 34,
          "column": 20
        }
      }
    }
  ],
  "tokens": [
    {
      "type": "CommentBlock",
      "value": "*\n* Set temperature.\n*\n* - set_temp [bed|hotend]\n*\n* ### on success\n* ```\n* return {\n*   \"device\": \"bed\",\n*   \"target\": 180\n* }\n* ```\n* ### on error\n* ```\n* return Error: '\"xxx\" is not a known temperature device.'\n* ```\n* @param  {String}   raw  Raw command response string.\n* @param  {String[]} args Command arguments.\n* @return {Object|Error}\n* @see https://github.com/Smoothieware/Smoothieware/blob/d79254323f4bb951426c6add29a4451130eaa018/src/modules/utils/simpleshell/SimpleShell.cpp#857\n",
      "start": 0,
      "end": 497,
      "loc": {
        "start": {
          "line": 1,
          "column": 0
        },
        "end": {
          "line": 21,
          "column": 2
        }
      }
    },
    {
      "type": {
        "label": "export",
        "keyword": "export",
        "beforeExpr": false,
        "startsExpr": false,
        "rightAssociative": false,
        "isLoop": false,
        "isAssign": false,
        "prefix": false,
        "postfix": false,
        "binop": null,
        "updateContext": null
      },
      "value": "export",
      "start": 498,
      "end": 504,
      "loc": {
        "start": {
          "line": 22,
          "column": 0
        },
        "end": {
          "line": 22,
          "column": 6
        }
      }
    },
    {
      "type": {
        "label": "function",
        "keyword": "function",
        "beforeExpr": false,
        "startsExpr": true,
        "rightAssociative": false,
        "isLoop": false,
        "isAssign": false,
        "prefix": false,
        "postfix": false,
        "binop": null
      },
      "value": "function",
      "start": 505,
      "end": 513,
      "loc": {
        "start": {
          "line": 22,
          "column": 7
        },
        "end": {
          "line": 22,
          "column": 15
        }
      }
    },
    {
      "type": {
        "label": "name",
        "beforeExpr": false,
        "startsExpr": true,
        "rightAssociative": false,
        "isLoop": false,
        "isAssign": false,
        "prefix": false,
        "postfix": false,
        "binop": null
      },
      "value": "cmd_set_temp",
      "start": 514,
      "end": 526,
      "loc": {
        "start": {
          "line": 22,
          "column": 16
        },
        "end": {
          "line": 22,
          "column": 28
        }
      }
    },
    {
      "type": {
        "label": "(",
        "beforeExpr": true,
        "startsExpr": true,
        "rightAssociative": false,
        "isLoop": false,
        "isAssign": false,
        "prefix": false,
        "postfix": false,
        "binop": null
      },
      "start": 526,
      "end": 527,
      "loc": {
        "start": {
          "line": 22,
          "column": 28
        },
        "end": {
          "line": 22,
          "column": 29
        }
      }
    },
    {
      "type": {
        "label": "name",
        "beforeExpr": false,
        "startsExpr": true,
        "rightAssociative": false,
        "isLoop": false,
        "isAssign": false,
        "prefix": false,
        "postfix": false,
        "binop": null
      },
      "value": "raw",
      "start": 527,
      "end": 530,
      "loc": {
        "start": {
          "line": 22,
          "column": 29
        },
        "end": {
          "line": 22,
          "column": 32
        }
      }
    },
    {
      "type": {
        "label": ",",
        "beforeExpr": true,
        "startsExpr": false,
        "rightAssociative": false,
        "isLoop": false,
        "isAssign": false,
        "prefix": false,
        "postfix": false,
        "binop": null,
        "updateContext": null
      },
      "start": 530,
      "end": 531,
      "loc": {
        "start": {
          "line": 22,
          "column": 32
        },
        "end": {
          "line": 22,
          "column": 33
        }
      }
    },
    {
      "type": {
        "label": "name",
        "beforeExpr": false,
        "startsExpr": true,
        "rightAssociative": false,
        "isLoop": false,
        "isAssign": false,
        "prefix": false,
        "postfix": false,
        "binop": null
      },
      "value": "args",
      "start": 532,
      "end": 536,
      "loc": {
        "start": {
          "line": 22,
          "column": 34
        },
        "end": {
          "line": 22,
          "column": 38
        }
      }
    },
    {
      "type": {
        "label": ")",
        "beforeExpr": false,
        "startsExpr": false,
        "rightAssociative": false,
        "isLoop": false,
        "isAssign": false,
        "prefix": false,
        "postfix": false,
        "binop": null
      },
      "start": 536,
      "end": 537,
      "loc": {
        "start": {
          "line": 22,
          "column": 38
        },
        "end": {
          "line": 22,
          "column": 39
        }
      }
    },
    {
      "type": {
        "label": "{",
        "beforeExpr": true,
        "startsExpr": true,
        "rightAssociative": false,
        "isLoop": false,
        "isAssign": false,
        "prefix": false,
        "postfix": false,
        "binop": null
      },
      "start": 538,
      "end": 539,
      "loc": {
        "start": {
          "line": 22,
          "column": 40
        },
        "end": {
          "line": 22,
          "column": 41
        }
      }
    },
    {
      "type": "CommentLine",
      "value": " raw response",
      "start": 542,
      "end": 557,
      "loc": {
        "start": {
          "line": 23,
          "column": 2
        },
        "end": {
          "line": 23,
          "column": 17
        }
      }
    },
    {
      "type": {
        "label": "name",
        "beforeExpr": false,
        "startsExpr": true,
        "rightAssociative": false,
        "isLoop": false,
        "isAssign": false,
        "prefix": false,
        "postfix": false,
        "binop": null
      },
      "value": "raw",
      "start": 560,
      "end": 563,
      "loc": {
        "start": {
          "line": 24,
          "column": 2
        },
        "end": {
          "line": 24,
          "column": 5
        }
      }
    },
    {
      "type": {
        "label": "=",
        "beforeExpr": true,
        "startsExpr": false,
        "rightAssociative": false,
        "isLoop": false,
        "isAssign": true,
        "prefix": false,
        "postfix": false,
        "binop": null,
        "updateContext": null
      },
      "value": "=",
      "start": 564,
      "end": 565,
      "loc": {
        "start": {
          "line": 24,
          "column": 6
        },
        "end": {
          "line": 24,
          "column": 7
        }
      }
    },
    {
      "type": {
        "label": "name",
        "beforeExpr": false,
        "startsExpr": true,
        "rightAssociative": false,
        "isLoop": false,
        "isAssign": false,
        "prefix": false,
        "postfix": false,
        "binop": null
      },
      "value": "raw",
      "start": 566,
      "end": 569,
      "loc": {
        "start": {
          "line": 24,
          "column": 8
        },
        "end": {
          "line": 24,
          "column": 11
        }
      }
    },
    {
      "type": {
        "label": ".",
        "beforeExpr": false,
        "startsExpr": false,
        "rightAssociative": false,
        "isLoop": false,
        "isAssign": false,
        "prefix": false,
        "postfix": false,
        "binop": null,
        "updateContext": null
      },
      "start": 569,
      "end": 570,
      "loc": {
        "start": {
          "line": 24,
          "column": 11
        },
        "end": {
          "line": 24,
          "column": 12
        }
      }
    },
    {
      "type": {
        "label": "name",
        "beforeExpr": false,
        "startsExpr": true,
        "rightAssociative": false,
        "isLoop": false,
        "isAssign": false,
        "prefix": false,
        "postfix": false,
        "binop": null
      },
      "value": "trim",
      "start": 570,
      "end": 574,
      "loc": {
        "start": {
          "line": 24,
          "column": 12
        },
        "end": {
          "line": 24,
          "column": 16
        }
      }
    },
    {
      "type": {
        "label": "(",
        "beforeExpr": true,
        "startsExpr": true,
        "rightAssociative": false,
        "isLoop": false,
        "isAssign": false,
        "prefix": false,
        "postfix": false,
        "binop": null
      },
      "start": 574,
      "end": 575,
      "loc": {
        "start": {
          "line": 24,
          "column": 16
        },
        "end": {
          "line": 24,
          "column": 17
        }
      }
    },
    {
      "type": {
        "label": ")",
        "beforeExpr": false,
        "startsExpr": false,
        "rightAssociative": false,
        "isLoop": false,
        "isAssign": false,
        "prefix": false,
        "postfix": false,
        "binop": null
      },
      "start": 575,
      "end": 576,
      "loc": {
        "start": {
          "line": 24,
          "column": 17
        },
        "end": {
          "line": 24,
          "column": 18
        }
      }
    },
    {
      "type": "CommentLine",
      "value": " device",
      "start": 580,
      "end": 589,
      "loc": {
        "start": {
          "line": 26,
          "column": 2
        },
        "end": {
          "line": 26,
          "column": 11
        }
      }
    },
    {
      "type": {
        "label": "let",
        "keyword": "let",
        "beforeExpr": false,
        "startsExpr": false,
        "rightAssociative": false,
        "isLoop": false,
        "isAssign": false,
        "prefix": false,
        "postfix": false,
        "binop": null,
        "updateContext": null
      },
      "value": "let",
      "start": 592,
      "end": 595,
      "loc": {
        "start": {
          "line": 27,
          "column": 2
        },
        "end": {
          "line": 27,
          "column": 5
        }
      }
    },
    {
      "type": {
        "label": "name",
        "beforeExpr": false,
        "startsExpr": true,
        "rightAssociative": false,
        "isLoop": false,
        "isAssign": false,
        "prefix": false,
        "postfix": false,
        "binop": null
      },
      "value": "device",
      "start": 596,
      "end": 602,
      "loc": {
        "start": {
          "line": 27,
          "column": 6
        },
        "end": {
          "line": 27,
          "column": 12
        }
      }
    },
    {
      "type": {
        "label": "=",
        "beforeExpr": true,
        "startsExpr": false,
        "rightAssociative": false,
        "isLoop": false,
        "isAssign": true,
        "prefix": false,
        "postfix": false,
        "binop": null,
        "updateContext": null
      },
      "value": "=",
      "start": 603,
      "end": 604,
      "loc": {
        "start": {
          "line": 27,
          "column": 13
        },
        "end": {
          "line": 27,
          "column": 14
        }
      }
    },
    {
      "type": {
        "label": "(",
        "beforeExpr": true,
        "startsExpr": true,
        "rightAssociative": false,
        "isLoop": false,
        "isAssign": false,
        "prefix": false,
        "postfix": false,
        "binop": null
      },
      "start": 605,
      "end": 606,
      "loc": {
        "start": {
          "line": 27,
          "column": 15
        },
        "end": {
          "line": 27,
          "column": 16
        }
      }
    },
    {
      "type": {
        "label": "name",
        "beforeExpr": false,
        "startsExpr": true,
        "rightAssociative": false,
        "isLoop": false,
        "isAssign": false,
        "prefix": false,
        "postfix": false,
        "binop": null
      },
      "value": "args",
      "start": 606,
      "end": 610,
      "loc": {
        "start": {
          "line": 27,
          "column": 16
        },
        "end": {
          "line": 27,
          "column": 20
        }
      }
    },
    {
      "type": {
        "label": ".",
        "beforeExpr": false,
        "startsExpr": false,
        "rightAssociative": false,
        "isLoop": false,
        "isAssign": false,
        "prefix": false,
        "postfix": false,
        "binop": null,
        "updateContext": null
      },
      "start": 610,
      "end": 611,
      "loc": {
        "start": {
          "line": 27,
          "column": 20
        },
        "end": {
          "line": 27,
          "column": 21
        }
      }
    },
    {
      "type": {
        "label": "name",
        "beforeExpr": false,
        "startsExpr": true,
        "rightAssociative": false,
        "isLoop": false,
        "isAssign": false,
        "prefix": false,
        "postfix": false,
        "binop": null
      },
      "value": "shift",
      "start": 611,
      "end": 616,
      "loc": {
        "start": {
          "line": 27,
          "column": 21
        },
        "end": {
          "line": 27,
          "column": 26
        }
      }
    },
    {
      "type": {
        "label": "(",
        "beforeExpr": true,
        "startsExpr": true,
        "rightAssociative": false,
        "isLoop": false,
        "isAssign": false,
        "prefix": false,
        "postfix": false,
        "binop": null
      },
      "start": 616,
      "end": 617,
      "loc": {
        "start": {
          "line": 27,
          "column": 26
        },
        "end": {
          "line": 27,
          "column": 27
        }
      }
    },
    {
      "type": {
        "label": ")",
        "beforeExpr": false,
        "startsExpr": false,
        "rightAssociative": false,
        "isLoop": false,
        "isAssign": false,
        "prefix": false,
        "postfix": false,
        "binop": null
      },
      "start": 617,
      "end": 618,
      "loc": {
        "start": {
          "line": 27,
          "column": 27
        },
        "end": {
          "line": 27,
          "column": 28
        }
      }
    },
    {
      "type": {
        "label": "||",
        "beforeExpr": true,
        "startsExpr": false,
        "rightAssociative": false,
        "isLoop": false,
        "isAssign": false,
        "prefix": false,
        "postfix": false,
        "binop": 1,
        "updateContext": null
      },
      "value": "||",
      "start": 619,
      "end": 621,
      "loc": {
        "start": {
          "line": 27,
          "column": 29
        },
        "end": {
          "line": 27,
          "column": 31
        }
      }
    },
    {
      "type": {
        "label": "string",
        "beforeExpr": false,
        "startsExpr": true,
        "rightAssociative": false,
        "isLoop": false,
        "isAssign": false,
        "prefix": false,
        "postfix": false,
        "binop": null,
        "updateContext": null
      },
      "value": "",
      "start": 622,
      "end": 624,
      "loc": {
        "start": {
          "line": 27,
          "column": 32
        },
        "end": {
          "line": 27,
          "column": 34
        }
      }
    },
    {
      "type": {
        "label": ")",
        "beforeExpr": false,
        "startsExpr": false,
        "rightAssociative": false,
        "isLoop": false,
        "isAssign": false,
        "prefix": false,
        "postfix": false,
        "binop": null
      },
      "start": 624,
      "end": 625,
      "loc": {
        "start": {
          "line": 27,
          "column": 34
        },
        "end": {
          "line": 27,
          "column": 35
        }
      }
    },
    {
      "type": {
        "label": ".",
        "beforeExpr": false,
        "startsExpr": false,
        "rightAssociative": false,
        "isLoop": false,
        "isAssign": false,
        "prefix": false,
        "postfix": false,
        "binop": null,
        "updateContext": null
      },
      "start": 625,
      "end": 626,
      "loc": {
        "start": {
          "line": 27,
          "column": 35
        },
        "end": {
          "line": 27,
          "column": 36
        }
      }
    },
    {
      "type": {
        "label": "name",
        "beforeExpr": false,
        "startsExpr": true,
        "rightAssociative": false,
        "isLoop": false,
        "isAssign": false,
        "prefix": false,
        "postfix": false,
        "binop": null
      },
      "value": "toLowerCase",
      "start": 626,
      "end": 637,
      "loc": {
        "start": {
          "line": 27,
          "column": 36
        },
        "end": {
          "line": 27,
          "column": 47
        }
      }
    },
    {
      "type": {
        "label": "(",
        "beforeExpr": true,
        "startsExpr": true,
        "rightAssociative": false,
        "isLoop": false,
        "isAssign": false,
        "prefix": false,
        "postfix": false,
        "binop": null
      },
      "start": 637,
      "end": 638,
      "loc": {
        "start": {
          "line": 27,
          "column": 47
        },
        "end": {
          "line": 27,
          "column": 48
        }
      }
    },
    {
      "type": {
        "label": ")",
        "beforeExpr": false,
        "startsExpr": false,
        "rightAssociative": false,
        "isLoop": false,
        "isAssign": false,
        "prefix": false,
        "postfix": false,
        "binop": null
      },
      "start": 638,
      "end": 639,
      "loc": {
        "start": {
          "line": 27,
          "column": 48
        },
        "end": {
          "line": 27,
          "column": 49
        }
      }
    },
    {
      "type": "CommentLine",
      "value": " error",
      "start": 643,
      "end": 651,
      "loc": {
        "start": {
          "line": 29,
          "column": 2
        },
        "end": {
          "line": 29,
          "column": 10
        }
      }
    },
    {
      "type": {
        "label": "if",
        "keyword": "if",
        "beforeExpr": false,
        "startsExpr": false,
        "rightAssociative": false,
        "isLoop": false,
        "isAssign": false,
        "prefix": false,
        "postfix": false,
        "binop": null,
        "updateContext": null
      },
      "value": "if",
      "start": 654,
      "end": 656,
      "loc": {
        "start": {
          "line": 30,
          "column": 2
        },
        "end": {
          "line": 30,
          "column": 4
        }
      }
    },
    {
      "type": {
        "label": "(",
        "beforeExpr": true,
        "startsExpr": true,
        "rightAssociative": false,
        "isLoop": false,
        "isAssign": false,
        "prefix": false,
        "postfix": false,
        "binop": null
      },
      "start": 657,
      "end": 658,
      "loc": {
        "start": {
          "line": 30,
          "column": 5
        },
        "end": {
          "line": 30,
          "column": 6
        }
      }
    },
    {
      "type": {
        "label": "name",
        "beforeExpr": false,
        "startsExpr": true,
        "rightAssociative": false,
        "isLoop": false,
        "isAssign": false,
        "prefix": false,
        "postfix": false,
        "binop": null
      },
      "value": "raw",
      "start": 658,
      "end": 661,
      "loc": {
        "start": {
          "line": 30,
          "column": 6
        },
        "end": {
          "line": 30,
          "column": 9
        }
      }
    },
    {
      "type": {
        "label": ".",
        "beforeExpr": false,
        "startsExpr": false,
        "rightAssociative": false,
        "isLoop": false,
        "isAssign": false,
        "prefix": false,
        "postfix": false,
        "binop": null,
        "updateContext": null
      },
      "start": 661,
      "end": 662,
      "loc": {
        "start": {
          "line": 30,
          "column": 9
        },
        "end": {
          "line": 30,
          "column": 10
        }
      }
    },
    {
      "type": {
        "label": "name",
        "beforeExpr": false,
        "startsExpr": true,
        "rightAssociative": false,
        "isLoop": false,
        "isAssign": false,
        "prefix": false,
        "postfix": false,
        "binop": null
      },
      "value": "endsWith",
      "start": 662,
      "end": 670,
      "loc": {
        "start": {
          "line": 30,
          "column": 10
        },
        "end": {
          "line": 30,
          "column": 18
        }
      }
    },
    {
      "type": {
        "label": "(",
        "beforeExpr": true,
        "startsExpr": true,
        "rightAssociative": false,
        "isLoop": false,
        "isAssign": false,
        "prefix": false,
        "postfix": false,
        "binop": null
      },
      "start": 670,
      "end": 671,
      "loc": {
        "start": {
          "line": 30,
          "column": 18
        },
        "end": {
          "line": 30,
          "column": 19
        }
      }
    },
    {
      "type": {
        "label": "string",
        "beforeExpr": false,
        "startsExpr": true,
        "rightAssociative": false,
        "isLoop": false,
        "isAssign": false,
        "prefix": false,
        "postfix": false,
        "binop": null,
        "updateContext": null
      },
      "value": "is not a known temperature device",
      "start": 671,
      "end": 706,
      "loc": {
        "start": {
          "line": 30,
          "column": 19
        },
        "end": {
          "line": 30,
          "column": 54
        }
      }
    },
    {
      "type": {
        "label": ")",
        "beforeExpr": false,
        "startsExpr": false,
        "rightAssociative": false,
        "isLoop": false,
        "isAssign": false,
        "prefix": false,
        "postfix": false,
        "binop": null
      },
      "start": 706,
      "end": 707,
      "loc": {
        "start": {
          "line": 30,
          "column": 54
        },
        "end": {
          "line": 30,
          "column": 55
        }
      }
    },
    {
      "type": {
        "label": ")",
        "beforeExpr": false,
        "startsExpr": false,
        "rightAssociative": false,
        "isLoop": false,
        "isAssign": false,
        "prefix": false,
        "postfix": false,
        "binop": null
      },
      "start": 707,
      "end": 708,
      "loc": {
        "start": {
          "line": 30,
          "column": 55
        },
        "end": {
          "line": 30,
          "column": 56
        }
      }
    },
    {
      "type": {
        "label": "{",
        "beforeExpr": true,
        "startsExpr": true,
        "rightAssociative": false,
        "isLoop": false,
        "isAssign": false,
        "prefix": false,
        "postfix": false,
        "binop": null
      },
      "start": 709,
      "end": 710,
      "loc": {
        "start": {
          "line": 30,
          "column": 57
        },
        "end": {
          "line": 30,
          "column": 58
        }
      }
    },
    {
      "type": {
        "label": "return",
        "keyword": "return",
        "beforeExpr": true,
        "startsExpr": false,
        "rightAssociative": false,
        "isLoop": false,
        "isAssign": false,
        "prefix": false,
        "postfix": false,
        "binop": null,
        "updateContext": null
      },
      "value": "return",
      "start": 715,
      "end": 721,
      "loc": {
        "start": {
          "line": 31,
          "column": 4
        },
        "end": {
          "line": 31,
          "column": 10
        }
      }
    },
    {
      "type": {
        "label": "new",
        "keyword": "new",
        "beforeExpr": true,
        "startsExpr": true,
        "rightAssociative": false,
        "isLoop": false,
        "isAssign": false,
        "prefix": false,
        "postfix": false,
        "binop": null,
        "updateContext": null
      },
      "value": "new",
      "start": 722,
      "end": 725,
      "loc": {
        "start": {
          "line": 31,
          "column": 11
        },
        "end": {
          "line": 31,
          "column": 14
        }
      }
    },
    {
      "type": {
        "label": "name",
        "beforeExpr": false,
        "startsExpr": true,
        "rightAssociative": false,
        "isLoop": false,
        "isAssign": false,
        "prefix": false,
        "postfix": false,
        "binop": null
      },
      "value": "Error",
      "start": 726,
      "end": 731,
      "loc": {
        "start": {
          "line": 31,
          "column": 15
        },
        "end": {
          "line": 31,
          "column": 20
        }
      }
    },
    {
      "type": {
        "label": "(",
        "beforeExpr": true,
        "startsExpr": true,
        "rightAssociative": false,
        "isLoop": false,
        "isAssign": false,
        "prefix": false,
        "postfix": false,
        "binop": null
      },
      "start": 731,
      "end": 732,
      "loc": {
        "start": {
          "line": 31,
          "column": 20
        },
        "end": {
          "line": 31,
          "column": 21
        }
      }
    },
    {
      "type": {
        "label": "string",
        "beforeExpr": false,
        "startsExpr": true,
        "rightAssociative": false,
        "isLoop": false,
        "isAssign": false,
        "prefix": false,
        "postfix": false,
        "binop": null,
        "updateContext": null
      },
      "value": "\"",
      "start": 732,
      "end": 735,
      "loc": {
        "start": {
          "line": 31,
          "column": 21
        },
        "end": {
          "line": 31,
          "column": 24
        }
      }
    },
    {
      "type": {
        "label": "+/-",
        "beforeExpr": true,
        "startsExpr": true,
        "rightAssociative": false,
        "isLoop": false,
        "isAssign": false,
        "prefix": true,
        "postfix": false,
        "binop": 9,
        "updateContext": null
      },
      "value": "+",
      "start": 736,
      "end": 737,
      "loc": {
        "start": {
          "line": 31,
          "column": 25
        },
        "end": {
          "line": 31,
          "column": 26
        }
      }
    },
    {
      "type": {
        "label": "name",
        "beforeExpr": false,
        "startsExpr": true,
        "rightAssociative": false,
        "isLoop": false,
        "isAssign": false,
        "prefix": false,
        "postfix": false,
        "binop": null
      },
      "value": "device",
      "start": 738,
      "end": 744,
      "loc": {
        "start": {
          "line": 31,
          "column": 27
        },
        "end": {
          "line": 31,
          "column": 33
        }
      }
    },
    {
      "type": {
        "label": "+/-",
        "beforeExpr": true,
        "startsExpr": true,
        "rightAssociative": false,
        "isLoop": false,
        "isAssign": false,
        "prefix": true,
        "postfix": false,
        "binop": 9,
        "updateContext": null
      },
      "value": "+",
      "start": 745,
      "end": 746,
      "loc": {
        "start": {
          "line": 31,
          "column": 34
        },
        "end": {
          "line": 31,
          "column": 35
        }
      }
    },
    {
      "type": {
        "label": "string",
        "beforeExpr": false,
        "startsExpr": true,
        "rightAssociative": false,
        "isLoop": false,
        "isAssign": false,
        "prefix": false,
        "postfix": false,
        "binop": null,
        "updateContext": null
      },
      "value": "\" is not a known temperature device.",
      "start": 747,
      "end": 785,
      "loc": {
        "start": {
          "line": 31,
          "column": 36
        },
        "end": {
          "line": 31,
          "column": 74
        }
      }
    },
    {
      "type": {
        "label": ")",
        "beforeExpr": false,
        "startsExpr": false,
        "rightAssociative": false,
        "isLoop": false,
        "isAssign": false,
        "prefix": false,
        "postfix": false,
        "binop": null
      },
      "start": 785,
      "end": 786,
      "loc": {
        "start": {
          "line": 31,
          "column": 74
        },
        "end": {
          "line": 31,
          "column": 75
        }
      }
    },
    {
      "type": {
        "label": "}",
        "beforeExpr": false,
        "startsExpr": false,
        "rightAssociative": false,
        "isLoop": false,
        "isAssign": false,
        "prefix": false,
        "postfix": false,
        "binop": null
      },
      "start": 789,
      "end": 790,
      "loc": {
        "start": {
          "line": 32,
          "column": 2
        },
        "end": {
          "line": 32,
          "column": 3
        }
      }
    },
    {
      "type": "CommentLine",
      "value": " new temperature",
      "start": 794,
      "end": 812,
      "loc": {
        "start": {
          "line": 34,
          "column": 2
        },
        "end": {
          "line": 34,
          "column": 20
        }
      }
    },
    {
      "type": {
        "label": "let",
        "keyword": "let",
        "beforeExpr": false,
        "startsExpr": false,
        "rightAssociative": false,
        "isLoop": false,
        "isAssign": false,
        "prefix": false,
        "postfix": false,
        "binop": null,
        "updateContext": null
      },
      "value": "let",
      "start": 815,
      "end": 818,
      "loc": {
        "start": {
          "line": 35,
          "column": 2
        },
        "end": {
          "line": 35,
          "column": 5
        }
      }
    },
    {
      "type": {
        "label": "name",
        "beforeExpr": false,
        "startsExpr": true,
        "rightAssociative": false,
        "isLoop": false,
        "isAssign": false,
        "prefix": false,
        "postfix": false,
        "binop": null
      },
      "value": "target",
      "start": 819,
      "end": 825,
      "loc": {
        "start": {
          "line": 35,
          "column": 6
        },
        "end": {
          "line": 35,
          "column": 12
        }
      }
    },
    {
      "type": {
        "label": "=",
        "beforeExpr": true,
        "startsExpr": false,
        "rightAssociative": false,
        "isLoop": false,
        "isAssign": true,
        "prefix": false,
        "postfix": false,
        "binop": null,
        "updateContext": null
      },
      "value": "=",
      "start": 826,
      "end": 827,
      "loc": {
        "start": {
          "line": 35,
          "column": 13
        },
        "end": {
          "line": 35,
          "column": 14
        }
      }
    },
    {
      "type": {
        "label": "name",
        "beforeExpr": false,
        "startsExpr": true,
        "rightAssociative": false,
        "isLoop": false,
        "isAssign": false,
        "prefix": false,
        "postfix": false,
        "binop": null
      },
      "value": "parseInt",
      "start": 828,
      "end": 836,
      "loc": {
        "start": {
          "line": 35,
          "column": 15
        },
        "end": {
          "line": 35,
          "column": 23
        }
      }
    },
    {
      "type": {
        "label": "(",
        "beforeExpr": true,
        "startsExpr": true,
        "rightAssociative": false,
        "isLoop": false,
        "isAssign": false,
        "prefix": false,
        "postfix": false,
        "binop": null
      },
      "start": 836,
      "end": 837,
      "loc": {
        "start": {
          "line": 35,
          "column": 23
        },
        "end": {
          "line": 35,
          "column": 24
        }
      }
    },
    {
      "type": {
        "label": "name",
        "beforeExpr": false,
        "startsExpr": true,
        "rightAssociative": false,
        "isLoop": false,
        "isAssign": false,
        "prefix": false,
        "postfix": false,
        "binop": null
      },
      "value": "args",
      "start": 837,
      "end": 841,
      "loc": {
        "start": {
          "line": 35,
          "column": 24
        },
        "end": {
          "line": 35,
          "column": 28
        }
      }
    },
    {
      "type": {
        "label": ".",
        "beforeExpr": false,
        "startsExpr": false,
        "rightAssociative": false,
        "isLoop": false,
        "isAssign": false,
        "prefix": false,
        "postfix": false,
        "binop": null,
        "updateContext": null
      },
      "start": 841,
      "end": 842,
      "loc": {
        "start": {
          "line": 35,
          "column": 28
        },
        "end": {
          "line": 35,
          "column": 29
        }
      }
    },
    {
      "type": {
        "label": "name",
        "beforeExpr": false,
        "startsExpr": true,
        "rightAssociative": false,
        "isLoop": false,
        "isAssign": false,
        "prefix": false,
        "postfix": false,
        "binop": null
      },
      "value": "shift",
      "start": 842,
      "end": 847,
      "loc": {
        "start": {
          "line": 35,
          "column": 29
        },
        "end": {
          "line": 35,
          "column": 34
        }
      }
    },
    {
      "type": {
        "label": "(",
        "beforeExpr": true,
        "startsExpr": true,
        "rightAssociative": false,
        "isLoop": false,
        "isAssign": false,
        "prefix": false,
        "postfix": false,
        "binop": null
      },
      "start": 847,
      "end": 848,
      "loc": {
        "start": {
          "line": 35,
          "column": 34
        },
        "end": {
          "line": 35,
          "column": 35
        }
      }
    },
    {
      "type": {
        "label": ")",
        "beforeExpr": false,
        "startsExpr": false,
        "rightAssociative": false,
        "isLoop": false,
        "isAssign": false,
        "prefix": false,
        "postfix": false,
        "binop": null
      },
      "start": 848,
      "end": 849,
      "loc": {
        "start": {
          "line": 35,
          "column": 35
        },
        "end": {
          "line": 35,
          "column": 36
        }
      }
    },
    {
      "type": {
        "label": "||",
        "beforeExpr": true,
        "startsExpr": false,
        "rightAssociative": false,
        "isLoop": false,
        "isAssign": false,
        "prefix": false,
        "postfix": false,
        "binop": 1,
        "updateContext": null
      },
      "value": "||",
      "start": 850,
      "end": 852,
      "loc": {
        "start": {
          "line": 35,
          "column": 37
        },
        "end": {
          "line": 35,
          "column": 39
        }
      }
    },
    {
      "type": {
        "label": "num",
        "beforeExpr": false,
        "startsExpr": true,
        "rightAssociative": false,
        "isLoop": false,
        "isAssign": false,
        "prefix": false,
        "postfix": false,
        "binop": null,
        "updateContext": null
      },
      "value": 0,
      "start": 853,
      "end": 854,
      "loc": {
        "start": {
          "line": 35,
          "column": 40
        },
        "end": {
          "line": 35,
          "column": 41
        }
      }
    },
    {
      "type": {
        "label": ")",
        "beforeExpr": false,
        "startsExpr": false,
        "rightAssociative": false,
        "isLoop": false,
        "isAssign": false,
        "prefix": false,
        "postfix": false,
        "binop": null
      },
      "start": 854,
      "end": 855,
      "loc": {
        "start": {
          "line": 35,
          "column": 41
        },
        "end": {
          "line": 35,
          "column": 42
        }
      }
    },
    {
      "type": {
        "label": "return",
        "keyword": "return",
        "beforeExpr": true,
        "startsExpr": false,
        "rightAssociative": false,
        "isLoop": false,
        "isAssign": false,
        "prefix": false,
        "postfix": false,
        "binop": null,
        "updateContext": null
      },
      "value": "return",
      "start": 859,
      "end": 865,
      "loc": {
        "start": {
          "line": 37,
          "column": 2
        },
        "end": {
          "line": 37,
          "column": 8
        }
      }
    },
    {
      "type": {
        "label": "{",
        "beforeExpr": true,
        "startsExpr": true,
        "rightAssociative": false,
        "isLoop": false,
        "isAssign": false,
        "prefix": false,
        "postfix": false,
        "binop": null
      },
      "start": 866,
      "end": 867,
      "loc": {
        "start": {
          "line": 37,
          "column": 9
        },
        "end": {
          "line": 37,
          "column": 10
        }
      }
    },
    {
      "type": {
        "label": "name",
        "beforeExpr": false,
        "startsExpr": true,
        "rightAssociative": false,
        "isLoop": false,
        "isAssign": false,
        "prefix": false,
        "postfix": false,
        "binop": null
      },
      "value": "device",
      "start": 868,
      "end": 874,
      "loc": {
        "start": {
          "line": 37,
          "column": 11
        },
        "end": {
          "line": 37,
          "column": 17
        }
      }
    },
    {
      "type": {
        "label": ",",
        "beforeExpr": true,
        "startsExpr": false,
        "rightAssociative": false,
        "isLoop": false,
        "isAssign": false,
        "prefix": false,
        "postfix": false,
        "binop": null,
        "updateContext": null
      },
      "start": 874,
      "end": 875,
      "loc": {
        "start": {
          "line": 37,
          "column": 17
        },
        "end": {
          "line": 37,
          "column": 18
        }
      }
    },
    {
      "type": {
        "label": "name",
        "beforeExpr": false,
        "startsExpr": true,
        "rightAssociative": false,
        "isLoop": false,
        "isAssign": false,
        "prefix": false,
        "postfix": false,
        "binop": null
      },
      "value": "target",
      "start": 876,
      "end": 882,
      "loc": {
        "start": {
          "line": 37,
          "column": 19
        },
        "end": {
          "line": 37,
          "column": 25
        }
      }
    },
    {
      "type": {
        "label": "}",
        "beforeExpr": false,
        "startsExpr": false,
        "rightAssociative": false,
        "isLoop": false,
        "isAssign": false,
        "prefix": false,
        "postfix": false,
        "binop": null
      },
      "start": 883,
      "end": 884,
      "loc": {
        "start": {
          "line": 37,
          "column": 26
        },
        "end": {
          "line": 37,
          "column": 27
        }
      }
    },
    {
      "type": {
        "label": "}",
        "beforeExpr": false,
        "startsExpr": false,
        "rightAssociative": false,
        "isLoop": false,
        "isAssign": false,
        "prefix": false,
        "postfix": false,
        "binop": null
      },
      "start": 885,
      "end": 886,
      "loc": {
        "start": {
          "line": 38,
          "column": 0
        },
        "end": {
          "line": 38,
          "column": 1
        }
      }
    },
    {
      "type": {
        "label": "eof",
        "beforeExpr": false,
        "startsExpr": false,
        "rightAssociative": false,
        "isLoop": false,
        "isAssign": false,
        "prefix": false,
        "postfix": false,
        "binop": null,
        "updateContext": null
      },
      "start": 887,
      "end": 887,
      "loc": {
        "start": {
          "line": 39,
          "column": 0
        },
        "end": {
          "line": 39,
          "column": 0
        }
      }
    }
  ]
}